Workbook

Sheet 설정 Settings
A1: 설정 Settings — 노란 칸만 고치세요 (edit the yellow cells only)
A2: 노란 칸 = 입력 · 회색 칸 = 자동 계산 또는 config에서 온 값 · "가정"과 "추정"은 근거 자료가 없는 값입니다 (decision memo §5.1). 모든 시장 가격은 검색 요약(snippet)이므로 직접 확인하세요. 세무·법률 자문이 아닙니다.
A3: 항목 | B3: Item | C3: 값 Value | D3: 단위 | E3: 근거·상태 Basis / status | F3: 출처 Source
A4: 브랜드·연락처 Brand & contact — 이메일·문자마다 이름, 우편 주소, 연락처, 수신거부 문구가 필요합니다 (CASL, F11–F13)
A5: 브랜드 (영문) | B5: Brand (EN) | C5: Neighbourhood Home Care | E5: {BRAND}. config/business.ts 기본값 (NEXT_PUBLIC_BRAND_EN). 인보이스에 나옵니다.
A6: 브랜드 (한글) | B6: Brand (KO) | C6: 우리동네 홈케어 | E6: {BRAND}. config/business.ts 기본값 (NEXT_PUBLIC_BRAND_KO). 상호 등록 필요 여부는 확인 필요 (memo §6).
A7: 우편 주소 | B7: Mailing address | C7: {MAILING_ADDRESS} | E7: CASL 필수: "the mailing address" (SOR/2012-36 s.2(1)(d), F13). 사서함(PO box)도 되는지는 규정에 없음 — 확인 필요. | F7: https://github.com/justicecanada/laws-lois-xml/blob/main/eng/regulations/SOR-2012-36.xml
A8: 전화 | B8: Phone | C8: {PHONE} | E8: {PHONE}
A9: 이메일 | B9: Email | C9: {EMAIL} | E9: {EMAIL}
A10: 웹사이트 | B10: Website | C10: {WEBSITE} | E10: {WEBSITE}
A11: e-Transfer 받을 이메일 | B11: e-Transfer email | C11: ='설정 Settings'!$C$9 | E11: 기본값은 위 이메일. 다른 주소로 받으면 직접 입력하세요.
A12: 카드 결제 받음? | B12: Card accepted? | C12: NO | E12: 카드 결제 서비스를 실제로 쓸 때만 YES. Stripe 캐나다 수수료 2.9% + $0.30 (F37, SECONDARY). | F12: https://github.com/kurtrgoddard/Bilingua-App/blob/b1f427aae94ef32e9f78ad5543dad81c330e7956/economy/research-pricing.md
A13: 도시 (빌드 기준) | B13: City (build) | C13: gta | E13: 가격·세율 기본값의 기준 도시. 바꾸려면 다시 빌드: node scripts/build-crm.mjs --city=ottawa
A14: 계획 시작일 | B14: Plan start (day 1) | C14: 46293 | E14: memo: Mon 2026-09-28
A15: 기준일 | B15: As-of date | C15: =TODAY() | E15: 보통 TODAY(). 날짜를 직접 넣으면 그날 기준으로 지표·킬 기준·DAILY 줄을 다시 계산합니다.
A17: 소비자 계약·CASL Consumer contracts & CASL (F11, F32) — 법률 자문 아님
A18: 방문 계약 취소 가능 기간 | B18: Door-signed cancellation period | C18: 10 | D18: 일 | E18: 온타리오 방문(direct) 계약: 서명한 사본을 받은 날부터 10일 안에 취소 가능 (F32, SNIPPET). 기간 중 작업한 경우의 효과는 조사 안 됨. | F18: https://www.ontario.ca/page/your-rights-when-signing-or-cancelling-contract
A19: 취소 시 환불 기한 | B19: Refund due after cancellation | C19: 15 | D19: 일 | E19: 취소하면 15일 안에 환불 (F32) | F19: https://www.ontario.ca/page/your-rights-when-signing-or-cancelling-contract
A20: 문의 후 묵시적 동의 기간 | B20: Implied consent after an inquiry | C20: 6 | D20: 개월 | E20: CASL s.10(10) (F11). 그 뒤 문자·이메일을 보내려면 다른 동의 근거(예: 명시적 동의)가 필요. | F20: https://github.com/justicecanada/laws-lois-xml/blob/main/eng/acts/E-1.6.xml
A21: 수신거부 처리 기한 | B21: Unsubscribe processing time | C21: 10 | D21: 영업일 | E21: CASL: 수신거부는 10영업일 안에 처리, 수신거부 방법은 60일 동안 유효 (F11) | F21: https://github.com/justicecanada/laws-lois-xml/blob/main/eng/acts/E-1.6.xml
A23: 세금 Tax (F7–F10) — 세무 자문 아님
A24: GST/HST 등록? | B24: HST registered | C24: NO | E24: NO가 기본. 4분기 합계 $30,000 전까지 소규모 사업자 (ETA s.148, F7). 자발적 등록은 1년간 취소 불가 (s.242(2), F8). YES면 인보이스에 세금 줄이 나타납니다. | F24: https://github.com/justicecanada/laws-lois-xml/blob/main/eng/acts/E-15.xml
A25: GST/HST 등록번호 | B25: GST/HST number | E25: 등록한 뒤에만 입력
A26: 세율 | B26: Tax rate | C26: 0.13 | E26: config/business.ts TAX_RULES (gta). 온타리오 HST 13% (ETA s.165, Sched. VIII, F8). | F26: https://github.com/justicecanada/laws-lois-xml/blob/main/eng/acts/E-15.xml
A27: 세금 이름 | B27: Tax label | C27: HST 13% | E27: config/business.ts TAX_RULES
A28: 소규모 사업자 기준 | B28: Small-supplier threshold | C28: 30000 | D28: $ | E28: 4분기 합계 테스트 + 단일 분기 테스트 (ETA s.148, F7) | F28: https://github.com/justicecanada/laws-lois-xml/blob/main/eng/acts/E-15.xml
A29: 4분기 합계 경고선 | B29: Rolling 4-quarter warning | C29: 25000 | D29: $ | E29: memo §10 item 15 (미리 준비하기 위한 경고선)
A30: 단일 분기 경고선 | B30: Single-quarter warning | C30: 20000 | D30: $ | E30: memo §10 item 15
A31: 플랫폼 수입을 과세매출에 포함? | B31: Count platform income in HST test | C31: YES | E31: 플랫폼 수입이 본인 과세 공급인지 확인 안 됨 (memo 5.5). 보수적으로 YES.
A32: CPP 적립률 (자영업) | B32: CPP rate (self-employed) | C32: 0.119 | E32: 9.9% + 2.0% = 11.9% (CPP Act, F9) | F32: https://github.com/justicecanada/laws-lois-xml/blob/main/eng/acts/C-8.xml
A33: CPP 기본 공제 | B33: CPP basic exemption | C33: 3500 | D33: $/년 | E33: F9. 적립 권장액은 보수적으로 이 공제를 무시합니다 (memo 5.4). | F33: https://github.com/justicecanada/laws-lois-xml/blob/main/eng/acts/C-8.xml
A34: 카드 수수료율 | B34: Card fee % | C34: 0.029 | E34: Stripe 캐나다 (F37, SECONDARY) | F34: https://github.com/kurtrgoddard/Bilingua-App/blob/b1f427aae94ef32e9f78ad5543dad81c330e7956/economy/research-pricing.md
A35: 카드 건당 수수료 | B35: Card fee per charge | C35: 0.3 | D35: $ | E35: Stripe 캐나다 (F37, SECONDARY) | F35: https://github.com/kurtrgoddard/Bilingua-App/blob/b1f427aae94ef32e9f78ad5543dad81c330e7956/economy/research-pricing.md
A36: e-Transfer 분할 안내 기준 | B36: Split e-Transfer above | C36: 2000 | D36: $ | E36: 은행별 한도 보통 $2,000–3,000 (F36, SECONDARY/사례). 넘으면 나눠 받기. | F36: https://github.com/nifabulous/Relay/blob/885bdf20a690d77dd2b93e46a52a597382039c6e/app/data/payment_schemes.py
A38: EI 고용보험 (memo 5.4, F1–F6) — 모든 계산은 추정. 판단은 Service Canada가 합니다
A39: EI 자격? | B39: EI eligible? | C39: UNKNOWN | E39: 보험가능 근로 420–700시간 필요. 비행(misconduct)이나 정당한 이유 없는 자진 퇴사는 자격 없음 (EI Act s.7(2), s.30(1), F6). 본인이 확인. NO면 EI 계산이 꺼집니다. | F39: https://github.com/justicecanada/laws-lois-xml/blob/main/eng/acts/E-5.6.xml
A40: EI 신청 마감 | B40: EI filing deadline | C40: 46305 | E40: Pilot 24: 2026-10-10까지 시작하는 수급 기간 (SOR-96-332 ss.77.996–77.999, F1). 연장 여부 찾지 못함. | F40: https://github.com/justicecanada/laws-lois-xml/blob/main/eng/regulations/SOR-96-332.xml
A41: EI 시작 주 (일요일) | B41: Benefit period start (Sunday) | C41: 46299 | E41: 10/10까지 신청하면 10/4 시작 (EI Act s.10(1), F2). 실제 날짜로 바꾸세요. | F41: https://github.com/justicecanada/laws-lois-xml/blob/main/eng/acts/E-5.6.xml
A42: 주간 EI 수령액 B | B42: Weekly benefit B | C42: 729 | D42: $/주 | E42: 예시 = 2026 최대치 (68,900 ÷ 52 × 55% = 728.75, F5 SECONDARY). 본인 실제 금액으로 바꾸세요. | F42: https://github.com/Artzp/RetireOps/blob/main/docs/source-of-truth/19-benefits-tax-credits-2026.md
A43: 주간 보험가능소득 | B43: Weekly insurable earnings | C43: 1325 | D43: $/주 | E43: 예시 = 최대 보험가능소득 68,900 ÷ 52 ≈ 1,325 (F5). 본인 금액으로 바꾸세요. | F43: https://github.com/Artzp/RetireOps/blob/main/docs/source-of-truth/19-benefits-tax-credits-2026.md
A44: 수입 공제율 | B44: Earnings deduction rate | C44: 0.5 | E44: 주간 보험가능소득의 90%까지는 50%, 그 위는 100% (EI Act s.19(2),(3), F4) | F44: https://github.com/justicecanada/laws-lois-xml/blob/main/eng/acts/E-5.6.xml
A45: 50% 구간 한도 | B45: 50% zone cap | C45: 0.9 | E45: 주간 보험가능소득의 90% (F4) | F45: https://github.com/justicecanada/laws-lois-xml/blob/main/eng/acts/E-5.6.xml
A46: Path A 계획 주간 순수입 A | B46: Planned Path A weekly net (A) | C46: 400 | D46: $/주 | E46: memo 5.4 예시 ($400). "경미한 정도(minor extent)" 인정 여부는 Service Canada에 전화로 확인 (Regs s.30, F3). | F46: https://github.com/justicecanada/laws-lois-xml/blob/main/eng/regulations/SOR-96-332.xml
A48: 문 두드리기 깔때기 Door funnel — 가정 (출처 없음, F45). 시도 30회부터 측정값으로 바뀝니다
A49: 응답률 (가정) | B49: Answer % (assumption A8) | C49: 0.35 | E49: 가정 A8 — 근거 자료 없음 (F45)
A50: 견적 요청률 (가정) | B50: Quote % (assumption A9) | C50: 0.1 | E50: 가정 A9 — 대화 중 견적 요청 비율
A51: 계약률 (가정) | B51: Close % (assumption A10) | C51: 0.4 | E51: 가정 A10 — 견적 중 계약 비율. 합치면 1.4% → 계약 1건당 약 71.4문
A52: 측정값 사용 최소 시도 | B52: Min attempts to use measured rates | C52: 30 | D52: 회 | E52: 이 수 이상이면 측정값 사용. 측정값이 0이면 그 비율만 가정값 사용.
A53: 시나리오 | B53: Scenario | C53: B1 | E53: B1 = 청소+플랫폼, B2 = G1 통과 후 홈통·제설 추가 (memo 5.2, 5.3)
A54: 다음 주 필요 계약 수 (직접) | B54: Closes needed next week (manual) | E54: 비워 두면 아래 주별 목표표에서 자동으로 가져옵니다 (memo §7).
A55: 다음 주 필요 계약 수 (사용값) | B55: Closes needed next week (used) | C55: =IF('설정 Settings'!$C$54<>"",'설정 Settings'!$C$54,IFERROR(IF('설정 Settings'!$C$15+14<=INDEX('설정 Settings'!$B$134:$B$141,MATCH('설정 Settings'!$C$15+14,'설정 Settings'!$A$134:$A$141,1)),IF('설정 Settings'!$C$53="B2",INDEX('설정 Settings'!$F$134:$F$141,MATCH('설정 Settings'!$C$15+14,'설정 Settings'!$A$134:$A$141,1)),INDEX('설정 Settings'!$D$134:$D$141,MATCH('설정 Settings'!$C$15+14,'설정 Settings'!$A$134:$A$141,1))),""),"")) | E55: = 그다음 주 완료 목표 (계약이 완료보다 약 1주 앞섬, memo §7 가정). 1월 이후는 직접 입력.
A56: 현재 클러스터 번호 | B56: Active cluster # | C56: 1 | E56: 지표 시트의 "남은 가구"는 이 클러스터 기준
A57: 클러스터 1 가구 수 | B57: Cluster 1 homes | C57: 2000 | D57: 가구 | E57: 추정: memo §7은 B1에 2,000가구 이상 권장. 실제로 세어서 바꾸세요.
A58: 클러스터 2 가구 수 | B58: Cluster 2 homes | C58: 0 | D58: 가구 | E58: 열 때 입력
A59: 클러스터 3 가구 수 | B59: Cluster 3 homes | C59: 0 | D59: 가구 | E59: 열 때 입력
A60: 문 1회 소요 시간 | B60: Minutes per door attempt | C60: 2 | D60: 분 | E60: 가정 A11
A61: 작업 있는 날 최대 문 | B61: Max doors on a job day | C61: 40 | D61: 문 | E61: memo §7 하루 한도
A62: 견적 후 후속 연락까지 | B62: Days before quote follow-up | C62: 2 | D62: 일 | E62: 운영 선택 (owner choice) — 근거 자료 없음
A64: 비용 가정 Costs — 추정 (출처 없음)
A65: 청소 직접비율 | B65: Cleaning direct cost % | C65: 0.2 | E65: 가정 A2 (청소 조사 자료의 임시값. 용품 가격은 못 찾음)
A66: 플랫폼 작업 직접비율 | B66: Platform direct cost % | C66: 0.1 | E66: 가정 A3 (용품·교통)
A67: 제설 직접비율 | B67: Snow direct cost % | C67: 0.15 | E67: 가정 A4 (소금·연료)
A68: 홈통 작업당 변동비 | B68: Gutter variable cost / job | C68: 20 | D68: $ | E68: 가정 A6 (출처 없음)
A69: 월 고정비 | B69: Monthly overhead | C69: 200 | D69: $/월 | E69: 가정 A7 (전화·인쇄·광고)
A70: 청소 CGL 보험료 (연) | B70: Cleaning CGL premium (yr) | C70: 500 | D70: $/년 | E70: "$500부터" (F23, SNIPPET). 실제 견적으로 바꾸세요. | F70: https://www.thinkinsure.ca/business-insurance/cleaning-insurance
A72: 손익분기 입력 Break-even inputs (memo 5.3) — 첫 시즌 기준, 추정
A73: 홈통 설비비 | B73: Gutter setup | C73: 1500 | D73: $ | E73: 가정 A5 (사다리·스태빌라이저·도구·블로어). 보험 제외. 캐나다 사다리 가격 못 찾음.
A74: 사다리·높이 보험 추가 | B74: Ladder / height cover | C74: 450 | D74: $ | E74: 창문 청소 $2M 약 $450/년 (F27 하한, SNIPPET). 홈통 전용 견적 못 찾음. | F74: https://rates.ca/insurance-quotes/business/contractor/window-cleaning
A75: 실제 사다리 보험 견적 | B75: Actual ladder cover quote | D75: $ | E75: 받으면 입력 (비우면 위 추정 사용)
A76: 홈통 가격 — 기본 | B76: Gutter ticket — base | C76: 225 | D76: $ | E76: config/prices.ts 2층 기본값 (memo 5.3 기본 $225). 가격표를 바꾸면 다시 빌드. | F76: https://professionalroofers.com/blogs/gutter-cleaning-cost-in-toronto-2025/
A77: 홈통 가격 — 보수 | B77: Gutter ticket — conservative | C77: 175 | D77: $ | E77: memo 5.1 보수 가정 ($150–350 범위 하단 근처)
A78: 제설 보험 — 기본 | B78: Snow cover — base | C78: 1000 | D78: $ | E78: "일반적" $1,000–3,000의 하단 (F29, SNIPPET) | F78: https://getcertain.ca/how-much-does-snow-removal-insurance-cost-in-canada/
A79: 제설 보험 — 보수 | B79: Snow cover — conservative | C79: 1800 | D79: $ | E79: "삽질하는 핸디맨 $1,800/년" (F29, 출처 불확실) | F79: https://getcertain.ca/how-much-does-snow-removal-insurance-cost-in-canada/
A80: 실제 제설 보험 견적 | B80: Actual snow cover quote | D80: $ | E80: 받으면 입력 (Gate S: 계약 전 서면 보험 필수)
A81: 제설기 — 기본 | B81: Snowblower — base | C81: 1299 | D81: $ | E81: 24" 2단 2025–26 할인가 $1,299–1,999 (F30, 포럼 요약) | F81: https://forums.redflagdeals.com/tags/snowblower/
A82: 제설기 — 보수 | B82: Snowblower — conservative | C82: 1999 | D82: $ | E82: F30 범위 상단 | F82: https://forums.redflagdeals.com/tags/snowblower/
A83: 실제 제설기 가격 | B83: Actual snowblower price | D83: $ | E83: 사면 입력 (11/20 손익분기 전에는 사지 않기)
A84: 제설 시즌 가격 — 기본 | B84: Snow season price — base | C84: 500 | D84: $ | E84: config/prices.ts 1열 진입로 (memo 5.3 기본 $500) | F84: https://silverlightwindowsandeaves.ca/how-much-does-snow-removal-cost-in-toronto/
A85: 제설 시즌 가격 — 보수 | B85: Snow season price — conservative | C85: 400 | D85: $ | E85: memo 5.1 보수 가정
A86: 11월 1회 방문 가격 | B86: November per-visit rate | C86: 60 | D86: $ | E86: config/prices.ts (memo: 기본 $60, F28 $50–150 범위에서 선택)
A87: 제설 분할 횟수 | B87: Snow instalments | C87: 4 | D87: 회 | E87: config/prices.ts: 12/1, 1/1, 2/1, 3/1 (memo §2)
A88: 제설 방식 | B88: Snow method | C88: BLOWER | E88: SHOVEL = 차 없이 삽만 (memo §2 Gate S, §9)
A89: 삽 제설 최대 곳 수 | B89: Shovel-only cap | C89: 10 | D89: 곳 | E89: 가정: 진입로 1곳 소요 시간을 재기 전까지 10곳 (memo §9)
A91: 게이트·점검 Gates & checks (memo §2, §8) — 상태를 직접 바꾸세요
A92: 청소 CGL 보험 가입됨? | B92: Cleaning CGL bound? | C92: NO | E92: 가입 전에는 직접 고객 금지 (memo §6). 사이트 "Insured" 표시도 가입 후에만.
A93: 플랫폼 승인됨? | B93: Platform approved? | C93: NO | E93: TaskRabbit/Jiffy 승인 기간 못 찾음 (F21)
A94: G1 통과? | B94: Gate G1 passed? | C94: PENDING | E94: 5개 모두: 차량, 사다리 가능, 브로커 서면 확인, 자금, 날짜 잡힌 홈통 예약 5건 (memo §2)
A95: G1 최소 홈통 예약 | B95: G1 min gutter bookings | C95: 5 | D95: 건 | E95: memo §2 G1 조건 5 — 사다리는 그 뒤에 구매
A96: 제설 서면 보험 (Gate S)? | B96: Gate S — written snow cover? | C96: NO | E96: 제설 계약 서명 전 필수. 목표 10/30 (memo §2)
A97: 현재 현금 | B97: Cash on hand | D97: $ | E97: 직접 입력 (매주 갱신)
A98: 최소 현금선 | B98: Runway floor | D98: $ | E98: 첫날 질문 10: 버틸 수 있는 월세 개월 수 기준 (memo §7)
A99: Day 7 점검일 | B99: Day 7 check | C99: 46299 | E99: memo §8
A100: Day 10 점검일 | B100: Day 10 check | C100: 46302 | E100: memo §8 (CGL 가입)
A101: G1 최종 마감 | B101: G1 hard stop | C101: 46304 | E101: memo §2
A102: Day 14 점검일 | B102: Day 14 check | C102: 46306 | E102: memo §8
A103: Day 21 점검일 | B103: Day 21 check | C103: 46313 | E103: memo §8
A104: Day 28 점검일 | B104: Day 28 check | C104: 46320 | E104: memo §8
A105: Day 30 점검일 | B105: Day 30 check | C105: 46322 | E105: memo §8
A106: 제설 손익분기 마감 | B106: Snow break-even deadline | C106: 46346 | E106: memo §2: 이날까지 손익분기 수 미달이면 모든 계약 무효
A107: Day 21 홈통 예약 구간 시작 | B107: Gutter booking window from | C107: 46314 | E107: memo §8
...

Sheet 문 두드리기 Doors
A1: 날짜 Date | B1: 거리 Street | C1: 집 번호 House # | D1: 시도 # Attempt # | E1: 결과 코드 Outcome | F1: 메모 Notes | G1: 클러스터 Cluster # | I1: 코드 | J1: 뜻 | K1: 할 일
A2: 46295 | B2: EXAMPLE St | C2: 101 | D2: 1 | E2: NA | F2: 예시 행 — 계산에서 제외됨 / EXAMPLE row, not counted | G2: 1 | I2: NA | J2: 부재 No answer | K2: 문고리 광고지를 두고 나중에 다시 (시도 # +1)
I3: NI | J3: 관심 없음 Not interested | K3: 끝. 다시 두드리지 않기
I4: Q | J4: 견적 요청 Quote requested | K4: 견적 시트에 한 줄 (출처 DOOR)
I5: B | J5: 바로 예약 Booked | K5: 견적 시트에 WON + 방문 계약 Y (10일 취소권 안내, F32)
I6: CB | J6: 다시 연락 Call back | K6: 후속 시트에 한 줄
I7: NS | J7: 방문판매 금지 표시 No soliciting | K7: 두드리지 않음. 시도 수에서 빠짐

Sheet 견적 Quotes
A1: 견적 ID Quote ID | B1: 요청일 Request date | C1: 출처 Source | D1: 고객 이름 Customer | E1: 주소 Address | F1: 연락처 Phone / email | G1: 서비스 Service | H1: 견적 금액 (세전) Quote $ (pre-tax) | I1: 상태 Status | J1: 계약일 Won date | K1: 작업 예정일 Scheduled | L1: 방문 계약? Door-signed (Y/N) | M1: 마케팅 수신 동의 Marketing opt-in (Y/N) | N1: 메모 Notes | O1: 취소 가능 기한 (추정) Cancel-by (est.) | P1: 예상 순이익 Est. net | Q1: 후속 알림 Follow-up
A2: EX-Q1 | B2: 46295 | C2: DOOR | D2: EXAMPLE Customer A | E2: 103 EXAMPLE St | F2: 555-0100 | G2: CL-DEEP | H2: 270 | I2: WON | J2: 46297 | K2: 46309 | L2: Y | M2: N | N2: 예시 행 — 계산에서 제외됨 / EXAMPLE row, not counted | O2: (자동) | P2: (자동) | Q2: (자동)
O3: =IF(AND($L3="Y",$J3<>""),$J3+'설정 Settings'!$C$18,"") | P3: =IF($H3="","",$H3-ROUND(IFERROR($H3*VLOOKUP($G3,'설정 Settings'!$A$122:$F$130,4,0)+VLOOKUP($G3,'설정 Settings'!$A$122:$F$130,5,0),0),2)) | Q3: =IF(AND($I3="OPEN",$B3<>""),IF('설정 Settings'!$C$15-$B3>='설정 Settings'!$C$62,"후속 연락 필요",""),"")
O4: =IF(AND($L4="Y",$J4<>""),$J4+'설정 Settings'!$C$18,"") | P4: =IF($H4="","",$H4-ROUND(IFERROR($H4*VLOOKUP($G4,'설정 Settings'!$A$122:$F$130,4,0)+VLOOKUP($G4,'설정 Settings'!$A$122:$F$130,5,0),0),2)) | Q4: =IF(AND($I4="OPEN",$B4<>""),IF('설정 Settings'!$C$15-$B4>='설정 Settings'!$C$62,"후속 연락 필요",""),"")
O5: =IF(AND($L5="Y",$J5<>""),$J5+'설정 Settings'!$C$18,"") | P5: =IF($H5="","",$H5-ROUND(IFERROR($H5*VLOOKUP($G5,'설정 Settings'!$A$122:$F$130,4,0)+VLOOKUP($G5,'설정 Settings'!$A$122:$F$130,5,0),0),2)) | Q5: =IF(AND($I5="OPEN",$B5<>""),IF('설정 Settings'!$C$15-$B5>='설정 Settings'!$C$62,"후속 연락 필요",""),"")
O6: =IF(AND($L6="Y",$J6<>""),$J6+'설정 Settings'!$C$18,"") | P6: =IF($H6="","",$H6-ROUND(IFERROR($H6*VLOOKUP($G6,'설정 Settings'!$A$122:$F$130,4,0)+VLOOKUP($G6,'설정 Settings'!$A$122:$F$130,5,0),0),2)) | Q6: =IF(AND($I6="OPEN",$B6<>""),IF('설정 Settings'!$C$15-$B6>='설정 Settings'!$C$62,"후속 연락 필요",""),"")
O7: =IF(AND($L7="Y",$J7<>""),$J7+'설정 Settings'!$C$18,"") | P7: =IF($H7="","",$H7-ROUND(IFERROR($H7*VLOOKUP($G7,'설정 Settings'!$A$122:$F$130,4,0)+VLOOKUP($G7,'설정 Settings'!$A$122:$F$130,5,0),0),2)) | Q7: =IF(AND($I7="OPEN",$B7<>""),IF('설정 Settings'!$C$15-$B7>='설정 Settings'!$C$62,"후속 연락 필요",""),"")
O8: =IF(AND($L8="Y",$J8<>""),$J8+'설정 Settings'!$C$18,"") | P8: =IF($H8="","",$H8-ROUND(IFERROR($H8*VLOOKUP($G8,'설정 Settings'!$A$122:$F$130,4,0)+VLOOKUP($G8,'설정 Settings'!$A$122:$F$130,5,0),0),2)) | Q8: =IF(AND($I8="OPEN",$B8<>""),IF('설정 Settings'!$C$15-$B8>='설정 Settings'!$C$62,"후속 연락 필요",""),"")
O9: =IF(AND($L9="Y",$J9<>""),$J9+'설정 Settings'!$C$18,"") | P9: =IF($H9="","",$H9-ROUND(IFERROR($H9*VLOOKUP($G9,'설정 Settings'!$A$122:$F$130,4,0)+VLOOKUP($G9,'설정 Settings'!$A$122:$F$130,5,0),0),2)) | Q9: =IF(AND($I9="OPEN",$B9<>""),IF('설정 Settings'!$C$15-$B9>='설정 Settings'!$C$62,"후속 연락 필요",""),"")
O10: =IF(AND($L10="Y",$J10<>""),$J10+'설정 Settings'!$C$18,"") | P10: =IF($H10="","",$H10-ROUND(IFERROR($H10*VLOOKUP($G10,'설정 Settings'!$A$122:$F$130,4,0)+VLOOKUP($G10,'설정 Settings'!$A$122:$F$130,5,0),0),2)) | Q10: =IF(AND($I10="OPEN",$B10<>""),IF('설정 Settings'!$C$15-$B10>='설정 Settings'!$C$62,"후속 연락 필요",""),"")
O11: =IF(AND($L11="Y",$J11<>""),$J11+'설정 Settings'!$C$18,"") | P11: =IF($H11="","",$H11-ROUND(IFERROR($H11*VLOOKUP($G11,'설정 Settings'!$A$122:$F$130,4,0)+VLOOKUP($G11,'설정 Settings'!$A$122:$F$130,5,0),0),2)) | Q11: =IF(AND($I11="OPEN",$B11<>""),IF('설정 Settings'!$C$15-$B11>='설정 Settings'!$C$62,"후속 연락 필요",""),"")
O12: =IF(AND($L12="Y",$J12<>""),$J12+'설정 Settings'!$C$18,"") | P12: =IF($H12="","",$H12-ROUND(IFERROR($H12*VLOOKUP($G12,'설정 Settings'!$A$122:$F$130,4,0)+VLOOKUP($G12,'설정 Settings'!$A$122:$F$130,5,0),0),2)) | Q12: =IF(AND($I12="OPEN",$B12<>""),IF('설정 Settings'!$C$15-$B12>='설정 Settings'!$C$62,"후속 연락 필요",""),"")
O13: =IF(AND($L13="Y",$J13<>""),$J13+'설정 Settings'!$C$18,"") | P13: =IF($H13="","",$H13-ROUND(IFERROR($H13*VLOOKUP($G13,'설정 Settings'!$A$122:$F$130,4,0)+VLOOKUP($G13,'설정 Settings'!$A$122:$F$130,5,0),0),2)) | Q13: =IF(AND($I13="OPEN",$B13<>""),IF('설정 Settings'!$C$15-$B13>='설정 Settings'!$C$62,"후속 연락 필요",""),"")
O14: =IF(AND($L14="Y",$J14<>""),$J14+'설정 Settings'!$C$18,"") | P14: =IF($H14="","",$H14-ROUND(IFERROR($H14*VLOOKUP($G14,'설정 Settings'!$A$122:$F$130,4,0)+VLOOKUP($G14,'설정 Settings'!$A$122:$F$130,5,0),0),2)) | Q14: =IF(AND($I14="OPEN",$B14<>""),IF('설정 Settings'!$C$15-$B14>='설정 Settings'!$C$62,"후속 연락 필요",""),"")
... O1002: =IF(AND($L1002="Y",$J1002<>""),$J1002+'설정 Settings'!$C$18,"") | P1002: =IF($H1002="","",$H1002-ROUND(IFERROR($H1002*VLOOKUP($G1002,'설정 Settings'!$A$122:$F$130,4,0)+VLOOKUP($G1002,'설정 Settings'!$A$122:$F$130,5,0),0),2)) | Q1002: =IF(AND($I1002="OPEN",$B1002<>""),IF('설정 Settings'!$C$15-$B1002>='설정 Settings'!$C$62,"후속 연락 필요",""),"")

Sheet 작업 Jobs
A1: 작업 ID Job ID | B1: 견적 ID Quote ID | C1: 완료일 Completed date | D1: 고객 이름 Customer | E1: 주소 Address | F1: 서비스 Service | G1: 출처 Source | H1: 금액 (세전) Price $ (pre-tax) | I1: 직접비 (실제) Direct costs $ (actual) | J1: 방문 계약? Door-signed (Y/N) | K1: 메모 Notes | L1: 적용 직접비 Direct cost used | M1: 순이익 Net | N1: 직접비 근거 Cost basis | O1: 입금 합계 Paid | P1: 미수금 Balance due | Q1: 인보이스 번호 Invoice # | R1: 분할 안내 Split note
A2: EX-J1 | B2: EX-Q1 | C2: 46309 | D2: EXAMPLE Customer A | E2: 103 EXAMPLE St | F2: CL-DEEP | G2: DOOR | H2: 270 | J2: Y | K2: 예시 행 — 계산에서 제외됨 / EXAMPLE row, not counted | L2: (자동) | M2: (자동) | N2: (자동) | O2: (자동) | P2: (자동) | Q2: (자동) | R2: (자동)
L3: =IF($C3="","",IF($I3="",ROUND(IFERROR($H3*VLOOKUP($F3,'설정 Settings'!$A$122:$F$130,4,0)+VLOOKUP($F3,'설정 Settings'!$A$122:$F$130,5,0),0),2),$I3)) | M3: =IF($C3="","",$H3-$L3) | N3: =IF($C3="","",IF($I3="","추정 ESTIMATE","실제 ACTUAL")) | O3: =IF($A3="","",SUMIFS('입금 Payments'!$C$3:$C$1002,'입금 Payments'!$B$3:$B$1002,$A3)) | P3: =IF($C3="","",ROUND($H3*(1+IF('설정 Settings'!$C$24="YES",'설정 Settings'!$C$26,0)),2)-N($O3)) | Q3: =IF($A3="","","INV-"&$A3) | R3: =IF($H3="","",IF($H3>'설정 Settings'!$C$36,"$2,000 초과: e-Transfer 나눠 받기 (F36)",""))
L4: =IF($C4="","",IF($I4="",ROUND(IFERROR($H4*VLOOKUP($F4,'설정 Settings'!$A$122:$F$130,4,0)+VLOOKUP($F4,'설정 Settings'!$A$122:$F$130,5,0),0),2),$I4)) | M4: =IF($C4="","",$H4-$L4) | N4: =IF($C4="","",IF($I4="","추정 ESTIMATE","실제 ACTUAL")) | O4: =IF($A4="","",SUMIFS('입금 Payments'!$C$3:$C$1002,'입금 Payments'!$B$3:$B$1002,$A4)) | P4: =IF($C4="","",ROUND($H4*(1+IF('설정 Settings'!$C$24="YES",'설정 Settings'!$C$26,0)),2)-N($O4)) | Q4: =IF($A4="","","INV-"&$A4) | R4: =IF($H4="","",IF($H4>'설정 Settings'!$C$36,"$2,000 초과: e-Transfer 나눠 받기 (F36)",""))
L5: =IF($C5="","",IF($I5="",ROUND(IFERROR($H5*VLOOKUP($F5,'설정 Settings'!$A$122:$F$130,4,0)+VLOOKUP($F5,'설정 Settings'!$A$122:$F$130,5,0),0),2),$I5)) | M5: =IF($C5="","",$H5-$L5) | N5: =IF($C5="","",IF($I5="","추정 ESTIMATE","실제 ACTUAL")) | O5: =IF($A5="","",SUMIFS('입금 Payments'!$C$3:$C$1002,'입금 Payments'!$B$3:$B$1002,$A5)) | P5: =IF($C5="","",ROUND($H5*(1+IF('설정 Settings'!$C$24="YES",'설정 Settings'!$C$26,0)),2)-N($O5)) | Q5: =IF($A5="","","INV-"&$A5) | R5: =IF($H5="","",IF($H5>'설정 Settings'!$C$36,"$2,000 초과: e-Transfer 나눠 받기 (F36)",""))
L6: =IF($C6="","",IF($I6="",ROUND(IFERROR($H6*VLOOKUP($F6,'설정 Settings'!$A$122:$F$130,4,0)+VLOOKUP($F6,'설정 Settings'!$A$122:$F$130,5,0),0),2),$I6)) | M6: =IF($C6="","",$H6-$L6) | N6: =IF($C6="","",IF($I6="","추정 ESTIMATE","실제 ACTUAL")) | O6: =IF($A6="","",SUMIFS('입금 Payments'!$C$3:$C$1002,'입금 Payments'!$B$3:$B$1002,$A6)) | P6: =IF($C6="","",ROUND($H6*(1+IF('설정 Settings'!$C$24="YES",'설정 Settings'!$C$26,0)),2)-N($O6)) | Q6: =IF($A6="","","INV-"&$A6) | R6: =IF($H6="","",IF($H6>'설정 Settings'!$C$36,"$2,000 초과: e-Transfer 나눠 받기 (F36)",""))
L7: =IF($C7="","",IF($I7="",ROUND(IFERROR($H7*VLOOKUP($F7,'설정 Settings'!$A$122:$F$130,4,0)+VLOOKUP($F7,'설정 Settings'!$A$122:$F$130,5,0),0),2),$I7)) | M7: =IF($C7="","",$H7-$L7) | N7: =IF($C7="","",IF($I7="","추정 ESTIMATE","실제 ACTUAL")) | O7: =IF($A7="","",SUMIFS('입금 Payments'!$C$3:$C$1002,'입금 Payments'!$B$3:$B$1002,$A7)) | P7: =IF($C7="","",ROUND($H7*(1+IF('설정 Settings'!$C$24="YES",'설정 Settings'!$C$26,0)),2)-N($O7)) | Q7: =IF($A7="","","INV-"&$A7) | R7: =IF($H7="","",IF($H7>'설정 Settings'!$C$36,"$2,000 초과: e-Transfer 나눠 받기 (F36)",""))
L8: =IF($C8="","",IF($I8="",ROUND(IFERROR($H8*VLOOKUP($F8,'설정 Settings'!$A$122:$F$130,4,0)+VLOOKUP($F8,'설정 Settings'!$A$122:$F$130,5,0),0),2),$I8)) | M8: =IF($C8="","",$H8-$L8) | N8: =IF($C8="","",IF($I8="","추정 ESTIMATE","실제 ACTUAL")) | O8: =IF($A8="","",SUMIFS('입금 Payments'!$C$3:$C$1002,'입금 Payments'!$B$3:$B$1002,$A8)) | P8: =IF($C8="","",ROUND($H8*(1+IF('설정 Settings'!$C$24="YES",'설정 Settings'!$C$26,0)),2)-N($O8)) | Q8: =IF($A8="","","INV-"&$A8) | R8: =IF($H8="","",IF($H8>'설정 Settings'!$C$36,"$2,000 초과: e-Transfer 나눠 받기 (F36)",""))
L9: =IF($C9="","",IF($I9="",ROUND(IFERROR($H9*VLOOKUP($F9,'설정 Settings'!$A$122:$F$130,4,0)+VLOOKUP($F9,'설정 Settings'!$A$122:$F$130,5,0),0),2),$I9)) | M9: =IF($C9="","",$H9-$L9) | N9: =IF($C9="","",IF($I9="","추정 ESTIMATE","실제 ACTUAL")) | O9: =IF($A9="","",SUMIFS('입금 Payments'!$C$3:$C$1002,'입금 Payments'!$B$3:$B$1002,$A9)) | P9: =IF($C9="","",ROUND($H9*(1+IF('설정 Settings'!$C$24="YES",'설정 Settings'!$C$26,0)),2)-N($O9)) | Q9: =IF($A9="","","INV-"&$A9) | R9: =IF($H9="","",IF($H9>'설정 Settings'!$C$36,"$2,000 초과: e-Transfer 나눠 받기 (F36)",""))
L10: =IF($C10="","",IF($I10="",ROUND(IFERROR($H10*VLOOKUP($F10,'설정 Settings'!$A$122:$F$130,4,0)+VLOOKUP($F10,'설정 Settings'!$A$122:$F$130,5,0),0),2),$I10)) | M10: =IF($C10="","",$H10-$L10) | N10: =IF($C10="","",IF($I10="","추정 ESTIMATE","실제 ACTUAL")) | O10: =IF($A10="","",SUMIFS('입금 Payments'!$C$3:$C$1002,'입금 Payments'!$B$3:$B$1002,$A10)) | P10: =IF($C10="","",ROUND($H10*(1+IF('설정 Settings'!$C$24="YES",'설정 Settings'!$C$26,0)),2)-N($O10)) | Q10: =IF($A10="","","INV-"&$A10) | R10: =IF($H10="","",IF($H10>'설정 Settings'!$C$36,"$2,000 초과: e-Transfer 나눠 받기 (F36)",""))
L11: =IF($C11="","",IF($I11="",ROUND(IFERROR($H11*VLOOKUP($F11,'설정 Settings'!$A$122:$F$130,4,0)+VLOOKUP($F11,'설정 Settings'!$A$122:$F$130,5,0),0),2),$I11)) | M11: =IF($C11="","",$H11-$L11) | N11: =IF($C11="","",IF($I11="","추정 ESTIMATE","실제 ACTUAL")) | O11: =IF($A11="","",SUMIFS('입금 Payments'!$C$3:$C$1002,'입금 Payments'!$B$3:$B$1002,$A11)) | P11: =IF($C11="","",ROUND($H11*(1+IF('설정 Settings'!$C$24="YES",'설정 Settings'!$C$26,0)),2)-N($O11)) | Q11: =IF($A11="","","INV-"&$A11) | R11: =IF($H11="","",IF($H11>'설정 Settings'!$C$36,"$2,000 초과: e-Transfer 나눠 받기 (F36)",""))
L12: =IF($C12="","",IF($I12="",ROUND(IFERROR($H12*VLOOKUP($F12,'설정 Settings'!$A$122:$F$130,4,0)+VLOOKUP($F12,'설정 Settings'!$A$122:$F$130,5,0),0),2),$I12)) | M12: =IF($C12="","",$H12-$L12) | N12: =IF($C12="","",IF($I12="","추정 ESTIMATE","실제 ACTUAL")) | O12: =IF($A12="","",SUMIFS('입금 Payments'!$C$3:$C$1002,'입금 Payments'!$B$3:$B$1002,$A12)) | P12: =IF($C12="","",ROUND($H12*(1+IF('설정 Settings'!$C$24="YES",'설정 Settings'!$C$26,0)),2)-N($O12)) | Q12: =IF($A12="","","INV-"&$A12) | R12: =IF($H12="","",IF($H12>'설정 Settings'!$C$36,"$2,000 초과: e-Transfer 나눠 받기 (F36)",""))
L13: =IF($C13="","",IF($I13="",ROUND(IFERROR($H13*VLOOKUP($F13,'설정 Settings'!$A$122:$F$130,4,0)+VLOOKUP($F13,'설정 Settings'!$A$122:$F$130,5,0),0),2),$I13)) | M13: =IF($C13="","",$H13-$L13) | N13: =IF($C13="","",IF($I13="","추정 ESTIMATE","실제 ACTUAL")) | O13: =IF($A13="","",SUMIFS('입금 Payments'!$C$3:$C$1002,'입금 Payments'!$B$3:$B$1002,$A13)) | P13: =IF($C13="","",ROUND($H13*(1+IF('설정 Settings'!$C$24="YES",'설정 Settings'!$C$26,0)),2)-N($O13)) | Q13: =IF($A13="","","INV-"&$A13) | R13: =IF($H13="","",IF($H13>'설정 Settings'!$C$36,"$2,000 초과: e-Transfer 나눠 받기 (F36)",""))
L14: =IF($C14="","",IF($I14="",ROUND(IFERROR($H14*VLOOKUP($F14,'설정 Settings'!$A$122:$F$130,4,0)+VLOOKUP($F14,'설정 Settings'!$A$122:$F$130,5,0),0),2),$I14)) | M14: =IF($C14="","",$H14-$L14) | N14: =IF($C14="","",IF($I14="","추정 ESTIMATE","실제 ACTUAL")) | O14: =IF($A14="","",SUMIFS('입금 Payments'!$C$3:$C$1002,'입금 Payments'!$B$3:$B$1002,$A14)) | P14: =IF($C14="","",ROUND($H14*(1+IF('설정 Settings'!$C$24="YES",'설정 Settings'!$C$26,0)),2)-N($O14)) | Q14: =IF($A14="","","INV-"&$A14) | R14: =IF($H14="","",IF($H14>'설정 Settings'!$C$36,"$2,000 초과: e-Transfer 나눠 받기 (F36)",""))
... L1002: =IF($C1002="","",IF($I1002="",ROUND(IFERROR($H1002*VLOOKUP($F1002,'설정 Settings'!$A$122:$F$130,4,0)+VLOOKUP($F1002,'설정 Settings'!$A$122:$F$130,5,0),0),2),$I1002)) | M1002: =IF($C1002="","",$H1002-$L1002) | N1002: =IF($C1002="","",IF($I1002="","추정 ESTIMATE","실제 ACTUAL")) | O1002: =IF($A1002="","",SUMIFS('입금 Payments'!$C$3:$C$1002,'입금 Payments'!$B$3:$B$1002,$A1002)) | P1002: =IF($C1002="","",ROUND($H1002*(1+IF('설정 Settings'!$C$24="YES",'설정 Settings'!$C$26,0)),2)-N($O1002)) | Q1002: =IF($A1002="","","INV-"&$A1002) | R1002: =IF($H1002="","",IF($H1002>'설정 Settings'!$C$36,"$2,000 초과: e-Transfer 나눠 받기 (F36)",""))

Sheet 입금 Payments
A1: 입금일 Date | B1: 작업 ID Job ID | C1: 금액 Amount $ | D1: 방법 Method | E1: 참조번호 Reference | F1: 메모 Notes | G1: 고객 (자동) Customer (auto) | H1: 카드 수수료 (추정) Card fee (est.) | I1: 분할 안내 Split note | J1: 작업 잔액 Job balance
A2: 46309 | B2: EX-J1 | C2: 270 | D2: ETRANSFER | E2: EXAMPLE-REF-001 | F2: 예시 행 — 계산에서 제외됨 / EXAMPLE row, not counted | G2: (자동) | H2: (자동) | I2: (자동) | J2: (자동)
G3: =IF($B3="","",IFERROR(INDEX('작업 Jobs'!$D$3:$D$1002,MATCH($B3,'작업 Jobs'!$A$3:$A$1002,0)),"작업 ID 없음")) | H3: =IF($C3="","",IF($D3="CARD",ROUND($C3*'설정 Settings'!$C$34+'설정 Settings'!$C$35,2),0)) | I3: =IF($C3="","",IF($C3>'설정 Settings'!$C$36,"$2,000 초과: 은행 한도 확인, 나눠 받기 (F36)","")) | J3: =IF($B3="","",IFERROR(INDEX('작업 Jobs'!$P$3:$P$1002,MATCH($B3,'작업 Jobs'!$A$3:$A$1002,0)),""))
G4: =IF($B4="","",IFERROR(INDEX('작업 Jobs'!$D$3:$D$1002,MATCH($B4,'작업 Jobs'!$A$3:$A$1002,0)),"작업 ID 없음")) | H4: =IF($C4="","",IF($D4="CARD",ROUND($C4*'설정 Settings'!$C$34+'설정 Settings'!$C$35,2),0)) | I4: =IF($C4="","",IF($C4>'설정 Settings'!$C$36,"$2,000 초과: 은행 한도 확인, 나눠 받기 (F36)","")) | J4: =IF($B4="","",IFERROR(INDEX('작업 Jobs'!$P$3:$P$1002,MATCH($B4,'작업 Jobs'!$A$3:$A$1002,0)),""))
G5: =IF($B5="","",IFERROR(INDEX('작업 Jobs'!$D$3:$D$1002,MATCH($B5,'작업 Jobs'!$A$3:$A$1002,0)),"작업 ID 없음")) | H5: =IF($C5="","",IF($D5="CARD",ROUND($C5*'설정 Settings'!$C$34+'설정 Settings'!$C$35,2),0)) | I5: =IF($C5="","",IF($C5>'설정 Settings'!$C$36,"$2,000 초과: 은행 한도 확인, 나눠 받기 (F36)","")) | J5: =IF($B5="","",IFERROR(INDEX('작업 Jobs'!$P$3:$P$1002,MATCH($B5,'작업 Jobs'!$A$3:$A$1002,0)),""))
G6: =IF($B6="","",IFERROR(INDEX('작업 Jobs'!$D$3:$D$1002,MATCH($B6,'작업 Jobs'!$A$3:$A$1002,0)),"작업 ID 없음")) | H6: =IF($C6="","",IF($D6="CARD",ROUND($C6*'설정 Settings'!$C$34+'설정 Settings'!$C$35,2),0)) | I6: =IF($C6="","",IF($C6>'설정 Settings'!$C$36,"$2,000 초과: 은행 한도 확인, 나눠 받기 (F36)","")) | J6: =IF($B6="","",IFERROR(INDEX('작업 Jobs'!$P$3:$P$1002,MATCH($B6,'작업 Jobs'!$A$3:$A$1002,0)),""))
G7: =IF($B7="","",IFERROR(INDEX('작업 Jobs'!$D$3:$D$1002,MATCH($B7,'작업 Jobs'!$A$3:$A$1002,0)),"작업 ID 없음")) | H7: =IF($C7="","",IF($D7="CARD",ROUND($C7*'설정 Settings'!$C$34+'설정 Settings'!$C$35,2),0)) | I7: =IF($C7="","",IF($C7>'설정 Settings'!$C$36,"$2,000 초과: 은행 한도 확인, 나눠 받기 (F36)","")) | J7: =IF($B7="","",IFERROR(INDEX('작업 Jobs'!$P$3:$P$1002,MATCH($B7,'작업 Jobs'!$A$3:$A$1002,0)),""))
G8: =IF($B8="","",IFERROR(INDEX('작업 Jobs'!$D$3:$D$1002,MATCH($B8,'작업 Jobs'!$A$3:$A$1002,0)),"작업 ID 없음")) | H8: =IF($C8="","",IF($D8="CARD",ROUND($C8*'설정 Settings'!$C$34+'설정 Settings'!$C$35,2),0)) | I8: =IF($C8="","",IF($C8>'설정 Settings'!$C$36,"$2,000 초과: 은행 한도 확인, 나눠 받기 (F36)","")) | J8: =IF($B8="","",IFERROR(INDEX('작업 Jobs'!$P$3:$P$1002,MATCH($B8,'작업 Jobs'!$A$3:$A$1002,0)),""))
G9: =IF($B9="","",IFERROR(INDEX('작업 Jobs'!$D$3:$D$1002,MATCH($B9,'작업 Jobs'!$A$3:$A$1002,0)),"작업 ID 없음")) | H9: =IF($C9="","",IF($D9="CARD",ROUND($C9*'설정 Settings'!$C$34+'설정 Settings'!$C$35,2),0)) | I9: =IF($C9="","",IF($C9>'설정 Settings'!$C$36,"$2,000 초과: 은행 한도 확인, 나눠 받기 (F36)","")) | J9: =IF($B9="","",IFERROR(INDEX('작업 Jobs'!$P$3:$P$1002,MATCH($B9,'작업 Jobs'!$A$3:$A$1002,0)),""))
G10: =IF($B10="","",IFERROR(INDEX('작업 Jobs'!$D$3:$D$1002,MATCH($B10,'작업 Jobs'!$A$3:$A$1002,0)),"작업 ID 없음")) | H10: =IF($C10="","",IF($D10="CARD",ROUND($C10*'설정 Settings'!$C$34+'설정 Settings'!$C$35,2),0)) | I10: =IF($C10="","",IF($C10>'설정 Settings'!$C$36,"$2,000 초과: 은행 한도 확인, 나눠 받기 (F36)","")) | J10: =IF($B10="","",IFERROR(INDEX('작업 Jobs'!$P$3:$P$1002,MATCH($B10,'작업 Jobs'!$A$3:$A$1002,0)),""))
G11: =IF($B11="","",IFERROR(INDEX('작업 Jobs'!$D$3:$D$1002,MATCH($B11,'작업 Jobs'!$A$3:$A$1002,0)),"작업 ID 없음")) | H11: =IF($C11="","",IF($D11="CARD",ROUND($C11*'설정 Settings'!$C$34+'설정 Settings'!$C$35,2),0)) | I11: =IF($C11="","",IF($C11>'설정 Settings'!$C$36,"$2,000 초과: 은행 한도 확인, 나눠 받기 (F36)","")) | J11: =IF($B11="","",IFERROR(INDEX('작업 Jobs'!$P$3:$P$1002,MATCH($B11,'작업 Jobs'!$A$3:$A$1002,0)),""))
G12: =IF($B12="","",IFERROR(INDEX('작업 Jobs'!$D$3:$D$1002,MATCH($B12,'작업 Jobs'!$A$3:$A$1002,0)),"작업 ID 없음")) | H12: =IF($C12="","",IF($D12="CARD",ROUND($C12*'설정 Settings'!$C$34+'설정 Settings'!$C$35,2),0)) | I12: =IF($C12="","",IF($C12>'설정 Settings'!$C$36,"$2,000 초과: 은행 한도 확인, 나눠 받기 (F36)","")) | J12: =IF($B12="","",IFERROR(INDEX('작업 Jobs'!$P$3:$P$1002,MATCH($B12,'작업 Jobs'!$A$3:$A$1002,0)),""))
G13: =IF($B13="","",IFERROR(INDEX('작업 Jobs'!$D$3:$D$1002,MATCH($B13,'작업 Jobs'!$A$3:$A$1002,0)),"작업 ID 없음")) | H13: =IF($C13="","",IF($D13="CARD",ROUND($C13*'설정 Settings'!$C$34+'설정 Settings'!$C$35,2),0)) | I13: =IF($C13="","",IF($C13>'설정 Settings'!$C$36,"$2,000 초과: 은행 한도 확인, 나눠 받기 (F36)","")) | J13: =IF($B13="","",IFERROR(INDEX('작업 Jobs'!$P$3:$P$1002,MATCH($B13,'작업 Jobs'!$A$3:$A$1002,0)),""))
G14: =IF($B14="","",IFERROR(INDEX('작업 Jobs'!$D$3:$D$1002,MATCH($B14,'작업 Jobs'!$A$3:$A$1002,0)),"작업 ID 없음")) | H14: =IF($C14="","",IF($D14="CARD",ROUND($C14*'설정 Settings'!$C$34+'설정 Settings'!$C$35,2),0)) | I14: =IF($C14="","",IF($C14>'설정 Settings'!$C$36,"$2,000 초과: 은행 한도 확인, 나눠 받기 (F36)","")) | J14: =IF($B14="","",IFERROR(INDEX('작업 Jobs'!$P$3:$P$1002,MATCH($B14,'작업 Jobs'!$A$3:$A$1002,0)),""))
... G1002: =IF($B1002="","",IFERROR(INDEX('작업 Jobs'!$D$3:$D$1002,MATCH($B1002,'작업 Jobs'!$A$3:$A$1002,0)),"작업 ID 없음")) | H1002: =IF($C1002="","",IF($D1002="CARD",ROUND($C1002*'설정 Settings'!$C$34+'설정 Settings'!$C$35,2),0)) | I1002: =IF($C1002="","",IF($C1002>'설정 Settings'!$C$36,"$2,000 초과: 은행 한도 확인, 나눠 받기 (F36)","")) | J1002: =IF($B1002="","",IFERROR(INDEX('작업 Jobs'!$P$3:$P$1002,MATCH($B1002,'작업 Jobs'!$A$3:$A$1002,0)),""))

Sheet 후속 Follow-ups
A1: 등록일 Created | B1: 고객 Customer | C1: 관련 ID Quote / Job ID | D1: 유형 Type | E1: 채널 Channel | F1: 예정일 Due | G1: 완료? Done (Y/N) | H1: 동의 근거 Consent basis | I1: 수신거부? Unsubscribed (Y/N) | J1: 결과 Result | K1: 메모 Notes | L1: 상태 Status | M1: CASL 확인 CASL check | N1: 문의 동의 만료 Inquiry consent ends
A2: 46296 | B2: EXAMPLE Customer B | C2: EX-Q2 | D2: QUOTE | E2: SMS | F2: 46298 | G2: N | H2: INQUIRY | I2: N | K2: 예시 행 — 계산에서 제외됨 / EXAMPLE row, not counted | L2: (자동) | M2: (자동) | N2: (자동)
L3: =IF($A3="","",IF($G3="Y","완료 DONE",IF($F3="","날짜 없음",IF($F3<'설정 Settings'!$C$15,"지남 OVERDUE",IF($F3='설정 Settings'!$C$15,"오늘 TODAY","예정 OPEN"))))) | M3: =IF($A3="","",IF($I3="Y","수신거부: 문자·이메일 보내지 않기",IF(OR($E3="SMS",$E3="EMAIL"),IF(OR($H3="",$H3="NONE"),"동의 근거 없음: 전화·방문만",IF($H3="INQUIRY",IF(N($N3)=0,"견적 요청일을 못 찾음: 관련 ID에 견적 ID(Q-…)를 넣었는지 확인",IF('설정 Settings'!$C$15>N($N3),"문의 후 6개월 지남: 다른 동의 근거 필요","OK: 이름·주소·연락처·수신거부 문구 넣기")),IF($H3="REFERRAL","소개 후 첫 메시지만 OK: 소개자 이름 + 이름·주소·연락처·수신거부 문구. 두 번째부터는 다른 동의 근거 필요",IF(AND($H3="REPLY",$D3<>"QUOTE",$D3<>"CALLBACK"),"문의에 대한 답장이 아님: EXPRESS 또는 INQUIRY 동의 필요","OK: 이름·주소·연락처·수신거부 문구 넣기")))),""))) | N3: =IF($H3="INQUIRY",IFERROR(EDATE(INDEX('견적 Quotes'!$B$3:$B$1002,MATCH($C3,'견적 Quotes'!$A$3:$A$1002,0)),'설정 Settings'!$C$20),""),"")
L4: =IF($A4="","",IF($G4="Y","완료 DONE",IF($F4="","날짜 없음",IF($F4<'설정 Settings'!$C$15,"지남 OVERDUE",IF($F4='설정 Settings'!$C$15,"오늘 TODAY","예정 OPEN"))))) | M4: =IF($A4="","",IF($I4="Y","수신거부: 문자·이메일 보내지 않기",IF(OR($E4="SMS",$E4="EMAIL"),IF(OR($H4="",$H4="NONE"),"동의 근거 없음: 전화·방문만",IF($H4="INQUIRY",IF(N($N4)=0,"견적 요청일을 못 찾음: 관련 ID에 견적 ID(Q-…)를 넣었는지 확인",IF('설정 Settings'!$C$15>N($N4),"문의 후 6개월 지남: 다른 동의 근거 필요","OK: 이름·주소·연락처·수신거부 문구 넣기")),IF($H4="REFERRAL","소개 후 첫 메시지만 OK: 소개자 이름 + 이름·주소·연락처·수신거부 문구. 두 번째부터는 다른 동의 근거 필요",IF(AND($H4="REPLY",$D4<>"QUOTE",$D4<>"CALLBACK"),"문의에 대한 답장이 아님: EXPRESS 또는 INQUIRY 동의 필요","OK: 이름·주소·연락처·수신거부 문구 넣기")))),""))) | N4: =IF($H4="INQUIRY",IFERROR(EDATE(INDEX('견적 Quotes'!$B$3:$B$1002,MATCH($C4,'견적 Quotes'!$A$3:$A$1002,0)),'설정 Settings'!$C$20),""),"")
L5: =IF($A5="","",IF($G5="Y","완료 DONE",IF($F5="","날짜 없음",IF($F5<'설정 Settings'!$C$15,"지남 OVERDUE",IF($F5='설정 Settings'!$C$15,"오늘 TODAY","예정 OPEN"))))) | M5: =IF($A5="","",IF($I5="Y","수신거부: 문자·이메일 보내지 않기",IF(OR($E5="SMS",$E5="EMAIL"),IF(OR($H5="",$H5="NONE"),"동의 근거 없음: 전화·방문만",IF($H5="INQUIRY",IF(N($N5)=0,"견적 요청일을 못 찾음: 관련 ID에 견적 ID(Q-…)를 넣었는지 확인",IF('설정 Settings'!$C$15>N($N5),"문의 후 6개월 지남: 다른 동의 근거 필요","OK: 이름·주소·연락처·수신거부 문구 넣기")),IF($H5="REFERRAL","소개 후 첫 메시지만 OK: 소개자 이름 + 이름·주소·연락처·수신거부 문구. 두 번째부터는 다른 동의 근거 필요",IF(AND($H5="REPLY",$D5<>"QUOTE",$D5<>"CALLBACK"),"문의에 대한 답장이 아님: EXPRESS 또는 INQUIRY 동의 필요","OK: 이름·주소·연락처·수신거부 문구 넣기")))),""))) | N5: =IF($H5="INQUIRY",IFERROR(EDATE(INDEX('견적 Quotes'!$B$3:$B$1002,MATCH($C5,'견적 Quotes'!$A$3:$A$1002,0)),'설정 Settings'!$C$20),""),"")
L6: =IF($A6="","",IF($G6="Y","완료 DONE",IF($F6="","날짜 없음",IF($F6<'설정 Settings'!$C$15,"지남 OVERDUE",IF($F6='설정 Settings'!$C$15,"오늘 TODAY","예정 OPEN"))))) | M6: =IF($A6="","",IF($I6="Y","수신거부: 문자·이메일 보내지 않기",IF(OR($E6="SMS",$E6="EMAIL"),IF(OR($H6="",$H6="NONE"),"동의 근거 없음: 전화·방문만",IF($H6="INQUIRY",IF(N($N6)=0,"견적 요청일을 못 찾음: 관련 ID에 견적 ID(Q-…)를 넣었는지 확인",IF('설정 Settings'!$C$15>N($N6),"문의 후 6개월 지남: 다른 동의 근거 필요","OK: 이름·주소·연락처·수신거부 문구 넣기")),IF($H6="REFERRAL","소개 후 첫 메시지만 OK: 소개자 이름 + 이름·주소·연락처·수신거부 문구. 두 번째부터는 다른 동의 근거 필요",IF(AND($H6="REPLY",$D6<>"QUOTE",$D6<>"CALLBACK"),"문의에 대한 답장이 아님: EXPRESS 또는 INQUIRY 동의 필요","OK: 이름·주소·연락처·수신거부 문구 넣기")))),""))) | N6: =IF($H6="INQUIRY",IFERROR(EDATE(INDEX('견적 Quotes'!$B$3:$B$1002,MATCH($C6,'견적 Quotes'!$A$3:$A$1002,0)),'설정 Settings'!$C$20),""),"")
L7: =IF($A7="","",IF($G7="Y","완료 DONE",IF($F7="","날짜 없음",IF($F7<'설정 Settings'!$C$15,"지남 OVERDUE",IF($F7='설정 Settings'!$C$15,"오늘 TODAY","예정 OPEN"))))) | M7: =IF($A7="","",IF($I7="Y","수신거부: 문자·이메일 보내지 않기",IF(OR($E7="SMS",$E7="EMAIL"),IF(OR($H7="",$H7="NONE"),"동의 근거 없음: 전화·방문만",IF($H7="INQUIRY",IF(N($N7)=0,"견적 요청일을 못 찾음: 관련 ID에 견적 ID(Q-…)를 넣었는지 확인",IF('설정 Settings'!$C$15>N($N7),"문의 후 6개월 지남: 다른 동의 근거 필요","OK: 이름·주소·연락처·수신거부 문구 넣기")),IF($H7="REFERRAL","소개 후 첫 메시지만 OK: 소개자 이름 + 이름·주소·연락처·수신거부 문구. 두 번째부터는 다른 동의 근거 필요",IF(AND($H7="REPLY",$D7<>"QUOTE",$D7<>"CALLBACK"),"문의에 대한 답장이 아님: EXPRESS 또는 INQUIRY 동의 필요","OK: 이름·주소·연락처·수신거부 문구 넣기")))),""))) | N7: =IF($H7="INQUIRY",IFERROR(EDATE(INDEX('견적 Quotes'!$B$3:$B$1002,MATCH($C7,'견적 Quotes'!$A$3:$A$1002,0)),'설정 Settings'!$C$20),""),"")
L8: =IF($A8="","",IF($G8="Y","완료 DONE",IF($F8="","날짜 없음",IF($F8<'설정 Settings'!$C$15,"지남 OVERDUE",IF($F8='설정 Settings'!$C$15,"오늘 TODAY","예정 OPEN"))))) | M8: =IF($A8="","",IF($I8="Y","수신거부: 문자·이메일 보내지 않기",IF(OR($E8="SMS",$E8="EMAIL"),IF(OR($H8="",$H8="NONE"),"동의 근거 없음: 전화·방문만",IF($H8="INQUIRY",IF(N($N8)=0,"견적 요청일을 못 찾음: 관련 ID에 견적 ID(Q-…)를 넣었는지 확인",IF('설정 Settings'!$C$15>N($N8),"문의 후 6개월 지남: 다른 동의 근거 필요","OK: 이름·주소·연락처·수신거부 문구 넣기")),IF($H8="REFERRAL","소개 후 첫 메시지만 OK: 소개자 이름 + 이름·주소·연락처·수신거부 문구. 두 번째부터는 다른 동의 근거 필요",IF(AND($H8="REPLY",$D8<>"QUOTE",$D8<>"CALLBACK"),"문의에 대한 답장이 아님: EXPRESS 또는 INQUIRY 동의 필요","OK: 이름·주소·연락처·수신거부 문구 넣기")))),""))) | N8: =IF($H8="INQUIRY",IFERROR(EDATE(INDEX('견적 Quotes'!$B$3:$B$1002,MATCH($C8,'견적 Quotes'!$A$3:$A$1002,0)),'설정 Settings'!$C$20),""),"")
L9: =IF($A9="","",IF($G9="Y","완료 DONE",IF($F9="","날짜 없음",IF($F9<'설정 Settings'!$C$15,"지남 OVERDUE",IF($F9='설정 Settings'!$C$15,"오늘 TODAY","예정 OPEN"))))) | M9: =IF($A9="","",IF($I9="Y","수신거부: 문자·이메일 보내지 않기",IF(OR($E9="SMS",$E9="EMAIL"),IF(OR($H9="",$H9="NONE"),"동의 근거 없음: 전화·방문만",IF($H9="INQUIRY",IF(N($N9)=0,"견적 요청일을 못 찾음: 관련 ID에 견적 ID(Q-…)를 넣었는지 확인",IF('설정 Settings'!$C$15>N($N9),"문의 후 6개월 지남: 다른 동의 근거 필요","OK: 이름·주소·연락처·수신거부 문구 넣기")),IF($H9="REFERRAL","소개 후 첫 메시지만 OK: 소개자 이름 + 이름·주소·연락처·수신거부 문구. 두 번째부터는 다른 동의 근거 필요",IF(AND($H9="REPLY",$D9<>"QUOTE",$D9<>"CALLBACK"),"문의에 대한 답장이 아님: EXPRESS 또는 INQUIRY 동의 필요","OK: 이름·주소·연락처·수신거부 문구 넣기")))),""))) | N9: =IF($H9="INQUIRY",IFERROR(EDATE(INDEX('견적 Quotes'!$B$3:$B$1002,MATCH($C9,'견적 Quotes'!$A$3:$A$1002,0)),'설정 Settings'!$C$20),""),"")
L10: =IF($A10="","",IF($G10="Y","완료 DONE",IF($F10="","날짜 없음",IF($F10<'설정 Settings'!$C$15,"지남 OVERDUE",IF($F10='설정 Settings'!$C$15,"오늘 TODAY","예정 OPEN"))))) | M10: =IF($A10="","",IF($I10="Y","수신거부: 문자·이메일 보내지 않기",IF(OR($E10="SMS",$E10="EMAIL"),IF(OR($H10="",$H10="NONE"),"동의 근거 없음: 전화·방문만",IF($H10="INQUIRY",IF(N($N10)=0,"견적 요청일을 못 찾음: 관련 ID에 견적 ID(Q-…)를 넣었는지 확인",IF('설정 Settings'!$C$15>N($N10),"문의 후 6개월 지남: 다른 동의 근거 필요","OK: 이름·주소·연락처·수신거부 문구 넣기")),IF($H10="REFERRAL","소개 후 첫 메시지만 OK: 소개자 이름 + 이름·주소·연락처·수신거부 문구. 두 번째부터는 다른 동의 근거 필요",IF(AND($H10="REPLY",$D10<>"QUOTE",$D10<>"CALLBACK"),"문의에 대한 답장이 아님: EXPRESS 또는 INQUIRY 동의 필요","OK: 이름·주소·연락처·수신거부 문구 넣기")))),""))) | N10: =IF($H10="INQUIRY",IFERROR(EDATE(INDEX('견적 Quotes'!$B$3:$B$1002,MATCH($C10,'견적 Quotes'!$A$3:$A$1002,0)),'설정 Settings'!$C$20),""),"")
L11: =IF($A11="","",IF($G11="Y","완료 DONE",IF($F11="","날짜 없음",IF($F11<'설정 Settings'!$C$15,"지남 OVERDUE",IF($F11='설정 Settings'!$C$15,"오늘 TODAY","예정 OPEN"))))) | M11: =IF($A11="","",IF($I11="Y","수신거부: 문자·이메일 보내지 않기",IF(OR($E11="SMS",$E11="EMAIL"),IF(OR($H11="",$H11="NONE"),"동의 근거 없음: 전화·방문만",IF($H11="INQUIRY",IF(N($N11)=0,"견적 요청일을 못 찾음: 관련 ID에 견적 ID(Q-…)를 넣었는지 확인",IF('설정 Settings'!$C$15>N($N11),"문의 후 6개월 지남: 다른 동의 근거 필요","OK: 이름·주소·연락처·수신거부 문구 넣기")),IF($H11="REFERRAL","소개 후 첫 메시지만 OK: 소개자 이름 + 이름·주소·연락처·수신거부 문구. 두 번째부터는 다른 동의 근거 필요",IF(AND($H11="REPLY",$D11<>"QUOTE",$D11<>"CALLBACK"),"문의에 대한 답장이 아님: EXPRESS 또는 INQUIRY 동의 필요","OK: 이름·주소·연락처·수신거부 문구 넣기")))),""))) | N11: =IF($H11="INQUIRY",IFERROR(EDATE(INDEX('견적 Quotes'!$B$3:$B$1002,MATCH($C11,'견적 Quotes'!$A$3:$A$1002,0)),'설정 Settings'!$C$20),""),"")
L12: =IF($A12="","",IF($G12="Y","완료 DONE",IF($F12="","날짜 없음",IF($F12<'설정 Settings'!$C$15,"지남 OVERDUE",IF($F12='설정 Settings'!$C$15,"오늘 TODAY","예정 OPEN"))))) | M12: =IF($A12="","",IF($I12="Y","수신거부: 문자·이메일 보내지 않기",IF(OR($E12="SMS",$E12="EMAIL"),IF(OR($H12="",$H12="NONE"),"동의 근거 없음: 전화·방문만",IF($H12="INQUIRY",IF(N($N12)=0,"견적 요청일을 못 찾음: 관련 ID에 견적 ID(Q-…)를 넣었는지 확인",IF('설정 Settings'!$C$15>N($N12),"문의 후 6개월 지남: 다른 동의 근거 필요","OK: 이름·주소·연락처·수신거부 문구 넣기")),IF($H12="REFERRAL","소개 후 첫 메시지만 OK: 소개자 이름 + 이름·주소·연락처·수신거부 문구. 두 번째부터는 다른 동의 근거 필요",IF(AND($H12="REPLY",$D12<>"QUOTE",$D12<>"CALLBACK"),"문의에 대한 답장이 아님: EXPRESS 또는 INQUIRY 동의 필요","OK: 이름·주소·연락처·수신거부 문구 넣기")))),""))) | N12: =IF($H12="INQUIRY",IFERROR(EDATE(INDEX('견적 Quotes'!$B$3:$B$1002,MATCH($C12,'견적 Quotes'!$A$3:$A$1002,0)),'설정 Settings'!$C$20),""),"")
L13: =IF($A13="","",IF($G13="Y","완료 DONE",IF($F13="","날짜 없음",IF($F13<'설정 Settings'!$C$15,"지남 OVERDUE",IF($F13='설정 Settings'!$C$15,"오늘 TODAY","예정 OPEN"))))) | M13: =IF($A13="","",IF($I13="Y","수신거부: 문자·이메일 보내지 않기",IF(OR($E13="SMS",$E13="EMAIL"),IF(OR($H13="",$H13="NONE"),"동의 근거 없음: 전화·방문만",IF($H13="INQUIRY",IF(N($N13)=0,"견적 요청일을 못 찾음: 관련 ID에 견적 ID(Q-…)를 넣었는지 확인",IF('설정 Settings'!$C$15>N($N13),"문의 후 6개월 지남: 다른 동의 근거 필요","OK: 이름·주소·연락처·수신거부 문구 넣기")),IF($H13="REFERRAL","소개 후 첫 메시지만 OK: 소개자 이름 + 이름·주소·연락처·수신거부 문구. 두 번째부터는 다른 동의 근거 필요",IF(AND($H13="REPLY",$D13<>"QUOTE",$D13<>"CALLBACK"),"문의에 대한 답장이 아님: EXPRESS 또는 INQUIRY 동의 필요","OK: 이름·주소·연락처·수신거부 문구 넣기")))),""))) | N13: =IF($H13="INQUIRY",IFERROR(EDATE(INDEX('견적 Quotes'!$B$3:$B$1002,MATCH($C13,'견적 Quotes'!$A$3:$A$1002,0)),'설정 Settings'!$C$20),""),"")
L14: =IF($A14="","",IF($G14="Y","완료 DONE",IF($F14="","날짜 없음",IF($F14<'설정 Settings'!$C$15,"지남 OVERDUE",IF($F14='설정 Settings'!$C$15,"오늘 TODAY","예정 OPEN"))))) | M14: =IF($A14="","",IF($I14="Y","수신거부: 문자·이메일 보내지 않기",IF(OR($E14="SMS",$E14="EMAIL"),IF(OR($H14="",$H14="NONE"),"동의 근거 없음: 전화·방문만",IF($H14="INQUIRY",IF(N($N14)=0,"견적 요청일을 못 찾음: 관련 ID에 견적 ID(Q-…)를 넣었는지 확인",IF('설정 Settings'!$C$15>N($N14),"문의 후 6개월 지남: 다른 동의 근거 필요","OK: 이름·주소·연락처·수신거부 문구 넣기")),IF($H14="REFERRAL","소개 후 첫 메시지만 OK: 소개자 이름 + 이름·주소·연락처·수신거부 문구. 두 번째부터는 다른 동의 근거 필요",IF(AND($H14="REPLY",$D14<>"QUOTE",$D14<>"CALLBACK"),"문의에 대한 답장이 아님: EXPRESS 또는 INQUIRY 동의 필요","OK: 이름·주소·연락처·수신거부 문구 넣기")))),""))) | N14: =IF($H14="INQUIRY",IFERROR(EDATE(INDEX('견적 Quotes'!$B$3:$B$1002,MATCH($C14,'견적 Quotes'!$A$3:$A$1002,0)),'설정 Settings'!$C$20),""),"")
... L1002: =IF($A1002="","",IF($G1002="Y","완료 DONE",IF($F1002="","날짜 없음",IF($F1002<'설정 Settings'!$C$15,"지남 OVERDUE",IF($F1002='설정 Settings'!$C$15,"오늘 TODAY","예정 OPEN"))))) | M1002: =IF($A1002="","",IF($I1002="Y","수신거부: 문자·이메일 보내지 않기",IF(OR($E1002="SMS",$E1002="EMAIL"),IF(OR($H1002="",$H1002="NONE"),"동의 근거 없음: 전화·방문만",IF($H1002="INQUIRY",IF(N($N1002)=0,"견적 요청일을 못 찾음: 관련 ID에 견적 ID(Q-…)를 넣었는지 확인",IF('설정 Settings'!$C$15>N($N1002),"문의 후 6개월 지남: 다른 동의 근거 필요","OK: 이름·주소·연락처·수신거부 문구 넣기")),IF($H1002="REFERRAL","소개 후 첫 메시지만 OK: 소개자 이름 + 이름·주소·연락처·수신거부 문구. 두 번째부터는 다른 동의 근거 필요",IF(AND($H1002="REPLY",$D1002<>"QUOTE",$D1002<>"CALLBACK"),"문의에 대한 답장이 아님: EXPRESS 또는 INQUIRY 동의 필요","OK: 이름·주소·연락처·수신거부 문구 넣기")))),""))) | N1002: =IF($H1002="INQUIRY",IFERROR(EDATE(INDEX('견적 Quotes'!$B$3:$B$1002,MATCH($C1002,'견적 Quotes'!$A$3:$A$1002,0)),'설정 Settings'!$C$20),""),"")

Sheet 지표 Dashboard
A1: ="지표 Dashboard — 기준일 "&YEAR('설정 Settings'!$C$15)&"-"&TEXT(MONTH('설정 Settings'!$C$15),"00")&"-"&TEXT(DAY('설정 Settings'!$C$15),"00")
A2: 모든 칸이 자동 계산입니다. 기준일은 설정 시트에서 바꿉니다. 비율·목표는 가정(memo A8–A10)으로 시작해 시도 30회부터 측정값으로 바뀝니다. 모든 결과는 추정이며 소득 보장이 아닙니다.
A4: 1. 문 두드리기 누적 Door funnel (전체 기록)
A5: 총 시도 Attempts | B5: =COUNTIFS('문 두드리기 Doors'!$E$3:$E$10002,"NA")+COUNTIFS('문 두드리기 Doors'!$E$3:$E$10002,"NI")+COUNTIFS('문 두드리기 Doors'!$E$3:$E$10002,"Q")+COUNTIFS('문 두드리기 Doors'!$E$3:$E$10002,"B")+COUNTIFS('문 두드리기 Doors'!$E$3:$E$10002,"CB") | D5: NA+NI+Q+B+CB. 재방문도 1회 (memo §7). NS는 제외.
A6: 응답 Answered | B6: =COUNTIFS('문 두드리기 Doors'!$E$3:$E$10002,"NI")+COUNTIFS('문 두드리기 Doors'!$E$3:$E$10002,"Q")+COUNTIFS('문 두드리기 Doors'!$E$3:$E$10002,"B")+COUNTIFS('문 두드리기 Doors'!$E$3:$E$10002,"CB") | D6: NI+Q+B+CB
A7: 문에서 견적 요청 Quote requests at door | B7: =COUNTIFS('문 두드리기 Doors'!$E$3:$E$10002,"Q")+COUNTIFS('문 두드리기 Doors'!$E$3:$E$10002,"B") | D7: Q+B
A8: 방문판매 금지 표시 NS | B8: =COUNTIFS('문 두드리기 Doors'!$E$3:$E$10002,"NS") | D8: 두드리지 않은 집
A9: 견적 시트: 문 출처 견적 Door quotes | B9: =COUNTIFS('견적 Quotes'!$C$3:$C$1002,"DOOR") | D9: Q·B마다 견적 시트에 한 줄씩 넣어야 맞습니다
A10: 문 출처 계약 Door closes (WON) | B10: =COUNTIFS('견적 Quotes'!$C$3:$C$1002,"DOOR",'견적 Quotes'!$I$3:$I$1002,"WON")
A11: 문 출처 완료 작업 Door jobs completed | B11: =COUNTIFS('작업 Jobs'!$G$3:$G$1002,"DOOR")
A12: 전체 완료 작업 All completed jobs | B12: =COUNT('작업 Jobs'!$C$3:$C$1002)
A14: 2. 전환율 Rates — 사용값 = 시도가 최소 기준 이상이고 측정값이 0보다 크면 측정값, 아니면 가정
A15: 지표 | B15: 측정 Measured | C15: 표본 n | D15: 가정 Assumed | E15: 사용 Used | F15: 설명
A16: 응답률 Answer % | B16: =IFERROR($B$6/$B$5,0) | C16: =$B$5 | D16: ='설정 Settings'!$C$49 | E16: =IF(AND($B$5>='설정 Settings'!$C$52,$B$16>0),$B$16,$D$16) | F16: 응답 ÷ 시도 (A8 가정 35%)
A17: 견적률 Quote % | B17: =IFERROR($B$7/$B$6,0) | C17: =$B$6 | D17: ='설정 Settings'!$C$50 | E17: =IF(AND($B$5>='설정 Settings'!$C$52,$B$17>0),$B$17,$D$17) | F17: 문에서 견적 요청 ÷ 응답 (A9 가정 10%)
A18: 계약률 Close % | B18: =IFERROR($B$10/$B$9,0) | C18: =$B$9 | D18: ='설정 Settings'!$C$51 | E18: =IF(AND($B$5>='설정 Settings'!$C$52,$B$18>0),$B$18,$D$18) | F18: 문 출처 WON ÷ 문 출처 견적 (진행 중 포함 — 보수적). 견적 10건 미만이면 흔들림이 큽니다 (A10 가정 40%)
A19: 문→계약 Door→close % | B19: =IFERROR($B$10/$B$5,0) | C19: =$B$5 | D19: =$D$16*$D$17*$D$18 | E19: =$E$16*$E$17*$E$18 | F19: 사용값 = 응답률 × 견적률 × 계약률 (가정이면 1.4%)
A20: 계약 1건당 문 Doors per close | B20: =IFERROR($B$5/$B$10,0) | C20: =$B$10 | D20: =IFERROR(1/$D$19,0) | E20: =IFERROR(1/$E$19,0) | F20: 가정이면 약 71.4문 (memo 5.1)
A21: 완료 1건당 문 Doors per completed job | B21: =IFERROR($B$5/$B$11,0) | C21: =$B$11 | F21: 문 출처 완료 작업 기준
A22: 측정값 사용 여부 | B22: =IF($B$5>='설정 Settings'!$C$52,"측정값 사용 (시도 "&$B$5&"회)","가정 사용 — 시도 "&$B$5&"/"&'설정 Settings'!$C$52)
A24: 3. 다음 주 문 목표 Next-week door target (memo §7) — 필요 문 수 = 필요 계약 ÷ (응답률 × 견적률 × 계약률)
A25: 시나리오 Scenario | B25: ='설정 Settings'!$C$53 | D25: 설정 시트
A26: 다음 주 필요 계약 수 Closes needed | B26: ='설정 Settings'!$C$55 | D26: 그다음 주 완료 목표 (설정 시트 주별 목표표 또는 직접 입력)
A27: 다음 주 문 목표 Door target next week | B27: =IF($B$26="","설정에서 입력 필요",ROUNDUP(IFERROR($B$26/$E$19,0),0)) | D27: 재방문 포함 시도 수. 광고·B2B에서 계약이 오면 더 적어도 됩니다 (memo §7: 상한값).
A28: 예상 노크 시간 (시간) Door hours | B28: =IFERROR(ROUND($B$27*'설정 Settings'!$C$60/60,1),0) | D28: 가정 A11: 1회 2분. 작업 있는 날은 최대 40문 (memo §7).
A29: 현재 클러스터 Active cluster | B29: ='설정 Settings'!$C$56
A30: 클러스터 가구 수 Homes in cluster | B30: =IFERROR(INDEX('설정 Settings'!$C$57:$C$59,$B$29),0) | D30: 설정 시트
A31: 최종 결과가 난 집 Homes with a final outcome | B31: =COUNTIFS('문 두드리기 Doors'!$E$3:$E$10002,"NI",'문 두드리기 Doors'!$G$3:$G$10002,$B$29)+COUNTIFS('문 두드리기 Doors'!$E$3:$E$10002,"Q",'문 두드리기 Doors'!$G$3:$G$10002,$B$29)+COUNTIFS('문 두드리기 Doors'!$E$3:$E$10002,"B",'문 두드리기 Doors'!$G$3:$G$10002,$B$29)+COUNTIFS('문 두드리기 Doors'!$E$3:$E$10002,"NS",'문 두드리기 Doors'!$G$3:$G$10002,$B$29)+IF($B$29=1,COUNTIFS('문 두드리기 Doors'!$E$3:$E$10002,"NI",'문 두드리기 Doors'!$G$3:$G$10002,"")+COUNTIFS('문 두드리기 Doors'!$E$3:$E$10002,"Q",'문 두드리기 Doors'!$G$3:$G$10002,"")+COUNTIFS('문 두드리기 Doors'!$E$3:$E$10002,"B",'문 두드리기 Doors'!$G$3:$G$10002,"")+COUNTIFS('문 두드리기 Doors'!$E$3:$E$10002,"NS",'문 두드리기 Doors'!$G$3:$G$10002,""),0) | D31: NI+Q+B+NS (클러스터 칸이 비면 1로 계산). NA·CB는 아직 끝나지 않은 집.
A32: 남은 가구 Homes left | B32: =$B$30-$B$31 | D32: 클러스터 가구 수 − 최종 결과가 난 집
A33: 클러스터 #2 필요? Open cluster #2? | B33: =IF(ISNUMBER($B$27),IF($B$32<2*$B$27,"클러스터 #2 열기 — 남은 가구 < 2 × 문 목표","OK — 현재 클러스터 유지"),"-") | D33: memo §7: 남은 가구 < 2 × 필요 문 수이면 클러스터 #2
A35: 4. 수입 Run-rate — 최근 7일 완료 작업의 순이익 (설비·연 보험료 제외, memo §8)
A36: 최근 7일 순이익 Trailing-7-day net | B36: =SUMIFS('작업 Jobs'!$M$3:$M$1002,'작업 Jobs'!$C$3:$C$1002,">="&('설정 Settings'!$C$15-6),'작업 Jobs'!$C$3:$C$1002,"<="&'설정 Settings'!$C$15) | D36: 작업 시트: 완료일이 기준일−6 ~ 기준일인 작업의 순이익 합
A37: 최근 7일 완료 건수 Jobs (7 days) | B37: =COUNTIFS('작업 Jobs'!$C$3:$C$1002,">="&('설정 Settings'!$C$15-6),'작업 Jobs'!$C$3:$C$1002,"<="&'설정 Settings'!$C$15)
A38: 월 환산 Monthly pace (×4.33, 추정) | B38: =$B$36*4.33 | D38: 추정: 한 달 ≈ 4.33주. 소득 보장 아님.
A39: 이번 달 순이익 Month-to-date net | B39: =SUMIFS('작업 Jobs'!$M$3:$M$1002,'작업 Jobs'!$C$3:$C$1002,">="&DATE(YEAR('설정 Settings'!$C$15),MONTH('설정 Settings'!$C$15),1),'작업 Jobs'!$C$3:$C$1002,"<="&'설정 Settings'!$C$15) | D39: 월 고정비(가정 A7)는 빼지 않은 값
A40: 미수금 합계 Unpaid balances | B40: =SUMIF('작업 Jobs'!$P$3:$P$1002,">0") | D40: 작업 시트 미수금 > 0 합계
A41: 진행 중 견적 Open quotes | B41: =COUNTIF('견적 Quotes'!$I$3:$I$1002,"OPEN")
A42: 지난 후속 연락 Overdue follow-ups | B42: =COUNTIF('후속 Follow-ups'!$L$3:$L$1002,"지남 OVERDUE")
A43: EI Path A / B 판단 | B43: ='EI 주간신고'!$R$14 | D43: EI 주간신고 시트 (memo 5.4). 판단은 Service Canada.
A45: 5. 킬 기준 Kill criteria (memo §8) — PASS 통과 · FAIL/ACTION 조치 · PENDING 아직 날짜 전
A46: 점검 Check | B46: 날짜 | C46: 신호 Signal | D46: 측정 D | E46: 측정 E | F46: 측정 F | G46: 기준 Threshold | H46: 결과 Result | I46: 조치 Action
A47: Day 7 | B47: ='설정 Settings'!$C$99 | C47: 시도(D) ≥ 기준인데 견적 요청(E) 0건 | D47: =COUNTIFS('문 두드리기 Doors'!$E$3:$E$10002,"NA",'문 두드리기 Doors'!$A$3:$A$10002,"<="&$B$47)+COUNTIFS('문 두드리기 Doors'!$E$3:$E$10002,"NI",'문 두드리기 Doors'!$A$3:$A$10002,"<="&$B$47)+COUNTIFS('문 두드리기 Doors'!$E$3:$E$10002,"Q",'문 두드리기 Doors'!$A$3:$A$10002,"<="&$B$47)+COUNTIFS('문 두드리기 Doors'!$E$3:$E$10002,"B",'문 두드리기 Doors'!$A$3:$A$10002,"<="&$B$47)+COUNTIFS('문 두드리기 Doors'!$E$3:$E$10002,"CB",'문 두드리기 Doors'!$A$3:$A$10002,"<="&$B$47) | E47: =COUNTIFS('견적 Quotes'!$B$3:$B$1002,"<="&$B$47) | G47: ="시도 ≥"&'설정 Settings'!$C$109&", 견적 0" | H47: =IF('설정 Settings'!$C$15<$B$47,"대기 PENDING",IF(AND($D$47>='설정 Settings'!$C$109,$E$47=0),"조치 ACTION","통과 PASS")) | I47: 중단 아님. 스크립트·제안·거리를 바꾸고, 노크 시간 절반을 한인 커뮤니티·부동산 채널로 돌리기.
A48: Day 10 | B48: ='설정 Settings'!$C$100 | C48: 청소 CGL 보험 가입(D) | D48: ='설정 Settings'!$C$92 | G48: ="YES" | H48: =IF('설정 Settings'!$C$92="YES","통과 PASS",IF('설정 Settings'!$C$15<$B$48,"대기 PENDING","실패 FAIL")) | I48: 직접 고객 받지 않기. 플랫폼만 하다가 순이익 $500이 모이면 다시 시도.
A49: G1 마감 | B49: ='설정 Settings'!$C$101 | C49: G1 5개 조건 모두 충족(D) | D49: ='설정 Settings'!$C$94 | G49: ="YES" | H49: =IF('설정 Settings'!$C$94="YES","통과 PASS",IF('설정 Settings'!$C$15<$B$49,"대기 PENDING","실패 FAIL")) | I49: 2026년 홈통 청소 접기. 제설은 Gate S로 따로 결정.
A50: Day 14 | B50: ='설정 Settings'!$C$102 | C50: 유료 완료(D) 0건, 예약(E) 기준 미만, 시도(F) ≥ 기준 | D50: =COUNTIFS('작업 Jobs'!$C$3:$C$1002,"<="&$B$50,'작업 Jobs'!$O$3:$O$1002,">0") | E50: =COUNTIFS('견적 Quotes'!$I$3:$I$1002,"WON",'견적 Quotes'!$J$3:$J$1002,"<="&$B$50) | F50: =COUNTIFS('문 두드리기 Doors'!$E$3:$E$10002,"NA",'문 두드리기 Doors'!$A$3:$A$10002,"<="&$B$50)+COUNTIFS('문 두드리기 Doors'!$E$3:$E$10002,"NI",'문 두드리기 Doors'!$A$3:$A$10002,"<="&$B$50)+COUNTIFS('문 두드리기 Doors'!$E$3:$E$10002,"Q",'문 두드리기 Doors'!$A$3:$A$10002,"<="&$B$50)+COUNTIFS('문 두드리기 Doors'!$E$3:$E$10002,"B",'문 두드리기 Doors'!$A$3:$A$10002,"<="&$B$50)+COUNTIFS('문 두드리기 Doors'!$E$3:$E$10002,"CB",'문 두드리기 Doors'!$A$3:$A$10002,"<="&$B$50) | G50: ="완료 0, 예약 <"&'설정 Settings'!$C$111&", 시도 ≥"&'설정 Settings'!$C$110 | H50: =IF('설정 Settings'!$C$15<$B$50,"대기 PENDING",IF(AND($D$50=0,$E$50<'설정 Settings'!$C$111,$F$50>='설정 Settings'!$C$110),"실패 FAIL → Plan C","통과 PASS")) | I50: Plan C: EI Path A(자격이 있으면) + 플랫폼 + 전일제 구직.
A51: Day 14 | B51: ='설정 Settings'!$C$102 | C51: 플랫폼 승인(D) | D51: ='설정 Settings'!$C$93 | G51: ="YES" | H51: =IF('설정 Settings'!$C$93="YES","통과 PASS",IF('설정 Settings'!$C$15<$B$51,"대기 PENDING","실패 FAIL")) | I51: 모든 예측에서 플랫폼 시간 빼기. 빨리 승인될 거라 기대하고 다른 곳에 재신청하지 않기.
A52: Day 21 (B1) | B52: ='설정 Settings'!$C$103 | C52: 완료(D) 기준 미만 또는 7일 run-rate(E) 기준 미만 | D52: =COUNTIFS('작업 Jobs'!$C$3:$C$1002,"<="&$B$52) | E52: =SUMIFS('작업 Jobs'!$M$3:$M$1002,'작업 Jobs'!$C$3:$C$1002,">="&($B$52-6),'작업 Jobs'!$C$3:$C$1002,"<="&$B$52) | G52: ="완료 ≥"&'설정 Settings'!$C$112&", run-rate ≥ $"&'설정 Settings'!$C$113 | H52: =IF('설정 Settings'!$C$15<$B$52,"대기 PENDING",IF(OR($D$52<'설정 Settings'!$C$112,$E$52<'설정 Settings'!$C$113),"실패 FAIL → Plan C","통과 PASS")) | I52: Plan C.
A53: Day 21 (B2) | B53: ='설정 Settings'!$C$103 | C53: 10/19–11/30 날짜 잡힌 홈통 예약(D) 기준 미만 | D53: =COUNTIFS('견적 Quotes'!$G$3:$G$1002,"GUT",'견적 Quotes'!$I$3:$I$1002,"WON",'견적 Quotes'!$K$3:$K$1002,">="&'설정 Settings'!$C$107,'견적 Quotes'!$K$3:$K$1002,"<="&'설정 Settings'!$C$108,'견적 Quotes'!$J$3:$J$1002,"<="&$B$53) | G53: ="≥"&'설정 Settings'!$C$114 | H53: =IF('설정 Settings'!$C$94<>"YES","해당 없음 N/A",IF('설정 Settings'!$C$15<$B$53,"대기 PENDING",IF($D$53<'설정 Settings'!$C$114,"실패 FAIL → 홈통 접기","통과 PASS"))) | I53: 홈통 접기. 사다리는 이미 샀을 때만 매몰비용.
A54: Day 21 (B2) | B54: ='설정 Settings'!$C$103 | C54: 문→계약률(D). E = 기본 B2 11월에 필요한 비율 | D54: =IFERROR(COUNTIFS('견적 Quotes'!$C$3:$C$1002,"DOOR",'견적 Quotes'!$I$3:$I$1002,"WON",'견적 Quotes'!$J$3:$J$1002,"<="&$B$54)/(COUNTIFS('문 두드리기 Doors'!$E$3:$E$10002,"NA",'문 두드리기 Doors'!$A$3:$A$10002,"<="&$B$54)+COUNTIFS('문 두드리기 Doors'!$E$3:$E$10002,"NI",'문 두드리기 Doors'!$A$3:$A$10002,"<="&$B$54)+COUNTIFS('문 두드리기 Doors'!$E$3:$E$10002,"Q",'문 두드리기 Doors'!$A$3:$A$10002,"<="&$B$54)+COUNTIFS('문 두드리기 Doors'!$E$3:$E$10002,"B",'문 두드리기 Doors'!$A$3:$A$10002,"<="&$B$54)+COUNTIFS('문 두드리기 Doors'!$E$3:$E$10002,"CB",'문 두드리기 Doors'!$A$3:$A$10002,"<="&$B$54)),0) | E54: ='설정 Settings'!$C$116 | G54: ="≥ "&TEXT('설정 Settings'!$C$115,"0.0%") | H54: =IF('설정 Settings'!$C$94<>"YES","해당 없음 N/A",IF('설정 Settings'!$C$15<$B$54,"대기 PENDING",IF($D$54<'설정 Settings'!$C$115,"조치 ACTION → 보수 시나리오","통과 PASS"))) | I54: 기본 B2 11월은 불가능(≥1.8% 필요, memo 5.3). 보수 시나리오 줄로 계획.
A55: Day 28 | B55: ='설정 Settings'!$C$104 | C55: 7일 run-rate(D) 기준 미만 | D55: =SUMIFS('작업 Jobs'!$M$3:$M$1002,'작업 Jobs'!$C$3:$C$1002,">="&($B$55-6),'작업 Jobs'!$C$3:$C$1002,"<="&$B$55) | G55: ="≥ $"&'설정 Settings'!$C$117&"/주" | H55: =IF('설정 Settings'!$C$15<$B$55,"대기 PENDING",IF($D$55<'설정 Settings'!$C$117,"실패 FAIL → Plan C","통과 PASS")) | I55: Plan C.
A56: Day 30 | B56: ='설정 Settings'!$C$105 | C56: 7일 run-rate(D) ≥ Path B 전환선(E, EI 시트) | D56: =SUMIFS('작업 Jobs'!$M$3:$M$1002,'작업 Jobs'!$C$3:$C$1002,">="&($B$56-6),'작업 Jobs'!$C$3:$C$1002,"<="&$B$56) | E56: ='EI 주간신고'!$R$9 | G56: ="≥ $"&ROUND('EI 주간신고'!$R$9,0)&"/주" | H56: =IF('설정 Settings'!$C$15<$B$56,"대기 PENDING",IF($D$56>=$E$56,"Path B (11월)","Path A 유지")) | I56: Path B = 사업 전념, 그 주 EI 없음 (F3). 모든 금액 신고. 판단은 Service Canada.
A57: 제설 11/20 | B57: ='설정 Settings'!$C$106 | C57: 11/20까지 서명한 제설 계약(D) < 손익분기(E) | D57: ='손익분기 Break-even'!$B$34 | E57: ='손익분기 Break-even'!$B$32 | G57: ="손익분기 수 이상" | H57: =IF(AND($D$57=0,'설정 Settings'!$C$96<>"YES"),"해당 없음 N/A",IF($D$57>=$E$57,"통과 PASS — 계약 유효",IF('설정 Settings'!$C$15<=$B$57,"대기 PENDING — "&MAX(0,$E$57-$D$57)&"건 더 필요","무효 VOID"))) | I57: 미달이면 모든 계약 무효 (받은 돈 없음). 보험·제설기 사지 않기.
A58: 매일 Any day | B58: ='설정 Settings'!$C$15 | C58: 현재 현금(D) < 최소 현금선(E) | D58: =IF('설정 Settings'!$C$97="","",'설정 Settings'!$C$97) | E58: =IF('설정 Settings'!$C$98="","",'설정 Settings'!$C$98) | G58: ="설정 시트" | H58: =IF(OR($D$58="",$E$58=""),"입력 필요 (설정)",IF($D$58<$E$58,"실패 FAIL — 구매 중단","통과 PASS")) | I58: 모든 설비 구매 중단. 플랫폼 + 구직만.
A60: 6. DAILY 이메일 제목 — 기준일 하루치 숫자. 아래 제목 줄을 그대로 복사해 본인에게 보내세요 (memo §10 item 11)
A61: 날짜 Date | B61: ='설정 Settings'!$C$15
A62: doors (시도, NS 제외) | B62: =COUNTIFS('문 두드리기 Doors'!$E$3:$E$10002,"NA",'문 두드리기 Doors'!$A$3:$A$10002,$B$61)+COUNTIFS('문 두드리기 Doors'!$E$3:$E$10002,"NI",'문 두드리기 Doors'!$A$3:$A$10002,$B$61)+COUNTIFS('문 두드리기 Doors'!$E$3:$E$10002,"Q",'문 두드리기 Doors'!$A$3:$A$10002,$B$61)+COUNTIFS('문 두드리기 Doors'!$E$3:$E$10002,"B",'문 두드리기 Doors'!$A$3:$A$10002,$B$61)+COUNTIFS('문 두드리기 Doors'!$E$3:$E$10002,"CB",'문 두드리기 Doors'!$A$3:$A$10002,$B$61)
A63: answers (응답) | B63: =COUNTIFS('문 두드리기 Doors'!$E$3:$E$10002,"NI",'문 두드리기 Doors'!$A$3:$A$10002,$B$61)+COUNTIFS('문 두드리기 Doors'!$E$3:$E$10002,"Q",'문 두드리기 Doors'!$A$3:$A$10002,$B$61)+COUNTIFS('문 두드리기 Doors'!$E$3:$E$10002,"B",'문 두드리기 Doors'!$A$3:$A$10002,$B$61)+COUNTIFS('문 두드리기 Doors'!$E$3:$E$10002,"CB",'문 두드리기 Doors'!$A$3:$A$10002,$B$61)
A64: quotes (새 견적 요청, 모든 출처) | B64: =COUNTIFS('견적 Quotes'!$B$3:$B$1002,$B$61)
A65: closes (그날 계약 성사) | B65: =COUNTIFS('견적 Quotes'!$J$3:$J$1002,$B$61,'견적 Quotes'!$I$3:$I$1002,"WON")
A66: completed (그날 완료한 작업) | B66: =COUNTIFS('작업 Jobs'!$C$3:$C$1002,$B$61)
A67: net (그날 완료 작업 순이익, 달러 반올림) | B67: =ROUND(SUMIFS('작업 Jobs'!$M$3:$M$1002,'작업 Jobs'!$C$3:$C$1002,$B$61),0)
A68: 이메일 제목 Subject | B68: ="DAILY "&YEAR($B$61)&"-"&TEXT(MONTH($B$61),"00")&"-"&TEXT(DAY($B$61),"00")&" doors="&$B$62&" answers="&$B$63&" quotes="&$B$64&" closes="&$B$65&" completed="&$B$66&" net="&$B$67

Sheet EI 주간신고
A1: EI 주간신고 — 추정 계산 (최종 판단은 Service Canada)
A2: 순수입 = 총수입 − 운영비 (EI Regs s.35(10)(c)); 수입은 일한 주에 배분 (s.36(6)); 모든 수입 신고, 신고 안 한 수입은 환수 (F4). 사업이 "경미한 정도(minor extent)"를 넘으면 그 주는 EI 없음 (s.30, F3). 총수입은 작업 시트, 운영비는 지출 시트에서 자동으로 옵니다. 법률 자문 아님.
A3: 주 시작 (일) Week start (Sun) | B3: 주 끝 (토) Week end | C3: 총수입 Gross | D3: 운영비 Operating exp. | E3: 순수입 Net = 총수입 − 운영비 | F3: 경로 Path | G3: EI 공제 추정 Est. deduction | H3: EI 수령 추정 Est. EI paid | I3: Path A 합계 EI + 순수입 | J3: CPP 뺀 합계 After CPP | K3: Path B 비교 (EI 없음, CPP 뺀) | L3: 이 주 기준 전환선 Switch line | M3: 신고함? Declared | N3: 신고일 Declared on | O3: 메모 Notes | Q3: 항목 Item | R3: 값 | S3: 근거
A4: 46292 | B4: =$A4+6 | C4: =SUMIFS('작업 Jobs'!$H$3:$H$1002,'작업 Jobs'!$C$3:$C$1002,">="&$A4,'작업 Jobs'!$C$3:$C$1002,"<="&$B4) | D4: =SUMIFS('지출 Expenses'!$D$3:$D$1002,'지출 Expenses'!$A$3:$A$1002,">="&$A4,'지출 Expenses'!$A$3:$A$1002,"<="&$B4) | E4: =$C4-$D4 | F4: =IF(OR('설정 Settings'!$C$39="NO",$A4<'설정 Settings'!$C$41),"-","A") | G4: =IF($E4<=0,0,'설정 Settings'!$C$44*MIN($E4,$R$6)+MAX(0,$E4-$R$6)) | H4: =IF($F4="A",MAX(0,$R$4-$G4),0) | I4: =$H4+$E4 | J4: =$H4+$E4-MAX(0,$E4)*$R$7 | K4: =$E4-MAX(0,$E4)*$R$7 | L4: =IFERROR(($R$4-'설정 Settings'!$C$44*$E4+(1-$R$7)*$E4)/(1-$R$7),"") | Q4: 주간 EI 수령액 B | R4: ='설정 Settings'!$C$42 | S4: 설정 시트 (예시 = 2026 최대 $729, F5)
A5: 46299 | B5: =$A5+6 | C5: =SUMIFS('작업 Jobs'!$H$3:$H$1002,'작업 Jobs'!$C$3:$C$1002,">="&$A5,'작업 Jobs'!$C$3:$C$1002,"<="&$B5) | D5: =SUMIFS('지출 Expenses'!$D$3:$D$1002,'지출 Expenses'!$A$3:$A$1002,">="&$A5,'지출 Expenses'!$A$3:$A$1002,"<="&$B5) | E5: =$C5-$D5 | F5: =IF(OR('설정 Settings'!$C$39="NO",$A5<'설정 Settings'!$C$41),"-","A") | G5: =IF($E5<=0,0,'설정 Settings'!$C$44*MIN($E5,$R$6)+MAX(0,$E5-$R$6)) | H5: =IF($F5="A",MAX(0,$R$4-$G5),0) | I5: =$H5+$E5 | J5: =$H5+$E5-MAX(0,$E5)*$R$7 | K5: =$E5-MAX(0,$E5)*$R$7 | L5: =IFERROR(($R$4-'설정 Settings'!$C$44*$E5+(1-$R$7)*$E5)/(1-$R$7),"") | Q5: 주간 보험가능소득 | R5: ='설정 Settings'!$C$43 | S5: 설정 시트
A6: 46306 | B6: =$A6+6 | C6: =SUMIFS('작업 Jobs'!$H$3:$H$1002,'작업 Jobs'!$C$3:$C$1002,">="&$A6,'작업 Jobs'!$C$3:$C$1002,"<="&$B6) | D6: =SUMIFS('지출 Expenses'!$D$3:$D$1002,'지출 Expenses'!$A$3:$A$1002,">="&$A6,'지출 Expenses'!$A$3:$A$1002,"<="&$B6) | E6: =$C6-$D6 | F6: =IF(OR('설정 Settings'!$C$39="NO",$A6<'설정 Settings'!$C$41),"-","A") | G6: =IF($E6<=0,0,'설정 Settings'!$C$44*MIN($E6,$R$6)+MAX(0,$E6-$R$6)) | H6: =IF($F6="A",MAX(0,$R$4-$G6),0) | I6: =$H6+$E6 | J6: =$H6+$E6-MAX(0,$E6)*$R$7 | K6: =$E6-MAX(0,$E6)*$R$7 | L6: =IFERROR(($R$4-'설정 Settings'!$C$44*$E6+(1-$R$7)*$E6)/(1-$R$7),"") | Q6: 50% 구간 한도 (90%) | R6: ='설정 Settings'!$C$43*'설정 Settings'!$C$45 | S6: F4
A7: 46313 | B7: =$A7+6 | C7: =SUMIFS('작업 Jobs'!$H$3:$H$1002,'작업 Jobs'!$C$3:$C$1002,">="&$A7,'작업 Jobs'!$C$3:$C$1002,"<="&$B7) | D7: =SUMIFS('지출 Expenses'!$D$3:$D$1002,'지출 Expenses'!$A$3:$A$1002,">="&$A7,'지출 Expenses'!$A$3:$A$1002,"<="&$B7) | E7: =$C7-$D7 | F7: =IF(OR('설정 Settings'!$C$39="NO",$A7<'설정 Settings'!$C$41),"-","A") | G7: =IF($E7<=0,0,'설정 Settings'!$C$44*MIN($E7,$R$6)+MAX(0,$E7-$R$6)) | H7: =IF($F7="A",MAX(0,$R$4-$G7),0) | I7: =$H7+$E7 | J7: =$H7+$E7-MAX(0,$E7)*$R$7 | K7: =$E7-MAX(0,$E7)*$R$7 | L7: =IFERROR(($R$4-'설정 Settings'!$C$44*$E7+(1-$R$7)*$E7)/(1-$R$7),"") | Q7: CPP 비율 | R7: ='설정 Settings'!$C$32 | S7: F9
A8: 46320 | B8: =$A8+6 | C8: =SUMIFS('작업 Jobs'!$H$3:$H$1002,'작업 Jobs'!$C$3:$C$1002,">="&$A8,'작업 Jobs'!$C$3:$C$1002,"<="&$B8) | D8: =SUMIFS('지출 Expenses'!$D$3:$D$1002,'지출 Expenses'!$A$3:$A$1002,">="&$A8,'지출 Expenses'!$A$3:$A$1002,"<="&$B8) | E8: =$C8-$D8 | F8: =IF(OR('설정 Settings'!$C$39="NO",$A8<'설정 Settings'!$C$41),"-","A") | G8: =IF($E8<=0,0,'설정 Settings'!$C$44*MIN($E8,$R$6)+MAX(0,$E8-$R$6)) | H8: =IF($F8="A",MAX(0,$R$4-$G8),0) | I8: =$H8+$E8 | J8: =$H8+$E8-MAX(0,$E8)*$R$7 | K8: =$E8-MAX(0,$E8)*$R$7 | L8: =IFERROR(($R$4-'설정 Settings'!$C$44*$E8+(1-$R$7)*$E8)/(1-$R$7),"") | Q8: Path A 계획 순수입 A | R8: ='설정 Settings'!$C$46 | S8: memo 5.4 예시 $400
A9: 46327 | B9: =$A9+6 | C9: =SUMIFS('작업 Jobs'!$H$3:$H$1002,'작업 Jobs'!$C$3:$C$1002,">="&$A9,'작업 Jobs'!$C$3:$C$1002,"<="&$B9) | D9: =SUMIFS('지출 Expenses'!$D$3:$D$1002,'지출 Expenses'!$A$3:$A$1002,">="&$A9,'지출 Expenses'!$A$3:$A$1002,"<="&$B9) | E9: =$C9-$D9 | F9: =IF(OR('설정 Settings'!$C$39="NO",$A9<'설정 Settings'!$C$41),"-","A") | G9: =IF($E9<=0,0,'설정 Settings'!$C$44*MIN($E9,$R$6)+MAX(0,$E9-$R$6)) | H9: =IF($F9="A",MAX(0,$R$4-$G9),0) | I9: =$H9+$E9 | J9: =$H9+$E9-MAX(0,$E9)*$R$7 | K9: =$E9-MAX(0,$E9)*$R$7 | L9: =IFERROR(($R$4-'설정 Settings'!$C$44*$E9+(1-$R$7)*$E9)/(1-$R$7),"") | Q9: Path B 전환선 (주) | R9: =IFERROR(($R$4-'설정 Settings'!$C$44*$R$8+(1-$R$7)*$R$8)/(1-$R$7),0) | S9: memo 5.4: (B − 0.5A + 0.881A) ÷ 0.881. 최대 EI면 약 $1,000
A10: 46334 | B10: =$A10+6 | C10: =SUMIFS('작업 Jobs'!$H$3:$H$1002,'작업 Jobs'!$C$3:$C$1002,">="&$A10,'작업 Jobs'!$C$3:$C$1002,"<="&$B10) | D10: =SUMIFS('지출 Expenses'!$D$3:$D$1002,'지출 Expenses'!$A$3:$A$1002,">="&$A10,'지출 Expenses'!$A$3:$A$1002,"<="&$B10) | E10: =$C10-$D10 | F10: =IF(OR('설정 Settings'!$C$39="NO",$A10<'설정 Settings'!$C$41),"-","A") | G10: =IF($E10<=0,0,'설정 Settings'!$C$44*MIN($E10,$R$6)+MAX(0,$E10-$R$6)) | H10: =IF($F10="A",MAX(0,$R$4-$G10),0) | I10: =$H10+$E10 | J10: =$H10+$E10-MAX(0,$E10)*$R$7 | K10: =$E10-MAX(0,$E10)*$R$7 | L10: =IFERROR(($R$4-'설정 Settings'!$C$44*$E10+(1-$R$7)*$E10)/(1-$R$7),"") | Q10: 공식 적용 확인 | R10: =IF($R$8>$R$6,"A가 90% 한도 초과 — 전환선 재계산 필요","OK") | S10: A가 50% 구간 안에 있어야 공식이 맞습니다
A11: 46341 | B11: =$A11+6 | C11: =SUMIFS('작업 Jobs'!$H$3:$H$1002,'작업 Jobs'!$C$3:$C$1002,">="&$A11,'작업 Jobs'!$C$3:$C$1002,"<="&$B11) | D11: =SUMIFS('지출 Expenses'!$D$3:$D$1002,'지출 Expenses'!$A$3:$A$1002,">="&$A11,'지출 Expenses'!$A$3:$A$1002,"<="&$B11) | E11: =$C11-$D11 | F11: =IF(OR('설정 Settings'!$C$39="NO",$A11<'설정 Settings'!$C$41),"-","A") | G11: =IF($E11<=0,0,'설정 Settings'!$C$44*MIN($E11,$R$6)+MAX(0,$E11-$R$6)) | H11: =IF($F11="A",MAX(0,$R$4-$G11),0) | I11: =$H11+$E11 | J11: =$H11+$E11-MAX(0,$E11)*$R$7 | K11: =$E11-MAX(0,$E11)*$R$7 | L11: =IFERROR(($R$4-'설정 Settings'!$C$44*$E11+(1-$R$7)*$E11)/(1-$R$7),"") | Q11: 지난 2주 완료 순이익 | R11: =SUMIFS('작업 Jobs'!$M$3:$M$1002,'작업 Jobs'!$C$3:$C$1002,">="&('설정 Settings'!$C$15-13),'작업 Jobs'!$C$3:$C$1002,"<="&'설정 Settings'!$C$15) | S11: 작업 시트 (기준일 포함 14일)
A12: 46348 | B12: =$A12+6 | C12: =SUMIFS('작업 Jobs'!$H$3:$H$1002,'작업 Jobs'!$C$3:$C$1002,">="&$A12,'작업 Jobs'!$C$3:$C$1002,"<="&$B12) | D12: =SUMIFS('지출 Expenses'!$D$3:$D$1002,'지출 Expenses'!$A$3:$A$1002,">="&$A12,'지출 Expenses'!$A$3:$A$1002,"<="&$B12) | E12: =$C12-$D12 | F12: =IF(OR('설정 Settings'!$C$39="NO",$A12<'설정 Settings'!$C$41),"-","A") | G12: =IF($E12<=0,0,'설정 Settings'!$C$44*MIN($E12,$R$6)+MAX(0,$E12-$R$6)) | H12: =IF($F12="A",MAX(0,$R$4-$G12),0) | I12: =$H12+$E12 | J12: =$H12+$E12-MAX(0,$E12)*$R$7 | K12: =$E12-MAX(0,$E12)*$R$7 | L12: =IFERROR(($R$4-'설정 Settings'!$C$44*$E12+(1-$R$7)*$E12)/(1-$R$7),"") | Q12: 앞으로 2주 예약 순이익 | R12: =SUMIFS('견적 Quotes'!$P$3:$P$1002,'견적 Quotes'!$I$3:$I$1002,"WON",'견적 Quotes'!$G$3:$G$1002,"<>SNOW",'견적 Quotes'!$K$3:$K$1002,">"&'설정 Settings'!$C$15,'견적 Quotes'!$K$3:$K$1002,"<="&('설정 Settings'!$C$15+14)) | S12: 견적 시트: WON + 예정일이 앞으로 14일 (추정 순이익). 제설 시즌 계약(SNOW)은 제외: 견적 금액이 12–3월에 나눠 버는 시즌 총액이라서입니다. 할부는 작업 시트에 회차마다 한 줄씩(12/1, 1/1, 2/1, 3/1) 넣으면 “지난 2주 완료”에 잡힙니다.
A13: 46355 | B13: =$A13+6 | C13: =SUMIFS('작업 Jobs'!$H$3:$H$1002,'작업 Jobs'!$C$3:$C$1002,">="&$A13,'작업 Jobs'!$C$3:$C$1002,"<="&$B13) | D13: =SUMIFS('지출 Expenses'!$D$3:$D$1002,'지출 Expenses'!$A$3:$A$1002,">="&$A13,'지출 Expenses'!$A$3:$A$1002,"<="&$B13) | E13: =$C13-$D13 | F13: =IF(OR('설정 Settings'!$C$39="NO",$A13<'설정 Settings'!$C$41),"-","A") | G13: =IF($E13<=0,0,'설정 Settings'!$C$44*MIN($E13,$R$6)+MAX(0,$E13-$R$6)) | H13: =IF($F13="A",MAX(0,$R$4-$G13),0) | I13: =$H13+$E13 | J13: =$H13+$E13-MAX(0,$E13)*$R$7 | K13: =$E13-MAX(0,$E13)*$R$7 | L13: =IFERROR(($R$4-'설정 Settings'!$C$44*$E13+(1-$R$7)*$E13)/(1-$R$7),"") | Q13: 주당 평균 (4주) | R13: =IFERROR(($R$11+$R$12)/4,0) | S13: 해석(추정): (지난 2주 완료 + 앞으로 2주 예약) ÷ 4주 (memo 5.4 규칙 3)
A14: 46362 | B14: =$A14+6 | C14: =SUMIFS('작업 Jobs'!$H$3:$H$1002,'작업 Jobs'!$C$3:$C$1002,">="&$A14,'작업 Jobs'!$C$3:$C$1002,"<="&$B14) | D14: =SUMIFS('지출 Expenses'!$D$3:$D$1002,'지출 Expenses'!$A$3:$A$1002,">="&$A14,'지출 Expenses'!$A$3:$A$1002,"<="&$B14) | E14: =$C14-$D14 | F14: =IF(OR('설정 Settings'!$C$39="NO",$A14<'설정 Settings'!$C$41),"-","A") | G14: =IF($E14<=0,0,'설정 Settings'!$C$44*MIN($E14,$R$6)+MAX(0,$E14-$R$6)) | H14: =IF($F14="A",MAX(0,$R$4-$G14),0) | I14: =$H14+$E14 | J14: =$H14+$E14-MAX(0,$E14)*$R$7 | K14: =$E14-MAX(0,$E14)*$R$7 | L14: =IFERROR(($R$4-'설정 Settings'!$C$44*$E14+(1-$R$7)*$E14)/(1-$R$7),"") | Q14: 판단 | R14: =IF('설정 Settings'!$C$39="NO","EI 없음 — Path B (사업 전념)",IF($R$13>=$R$9,"Path B 전환 검토 (주 $"&ROUND($R$9,0)&" 이상)","Path A 유지")) | S14: 10월 기본값은 Path A (memo 5.4). Service Canada에 "minor extent" 여부를 먼저 전화로 물어보세요.
A15: 46369 | B15: =$A15+6 | C15: =SUMIFS('작업 Jobs'!$H$3:$H$1002,'작업 Jobs'!$C$3:$C$1002,">="&$A15,'작업 Jobs'!$C$3:$C$1002,"<="&$B15) | D15: =SUMIFS('지출 Expenses'!$D$3:$D$1002,'지출 Expenses'!$A$3:$A$1002,">="&$A15,'지출 Expenses'!$A$3:$A$1002,"<="&$B15) | E15: =$C15-$D15 | F15: =IF(OR('설정 Settings'!$C$39="NO",$A15<'설정 Settings'!$C$41),"-","A") | G15: =IF($E15<=0,0,'설정 Settings'!$C$44*MIN($E15,$R$6)+MAX(0,$E15-$R$6)) | H15: =IF($F15="A",MAX(0,$R$4-$G15),0) | I15: =$H15+$E15 | J15: =$H15+$E15-MAX(0,$E15)*$R$7 | K15: =$E15-MAX(0,$E15)*$R$7 | L15: =IFERROR(($R$4-'설정 Settings'!$C$44*$E15+(1-$R$7)*$E15)/(1-$R$7),"") | Q15: EI 신청 마감 | R15: ='설정 Settings'!$C$40 | S15: F1 (Pilot 24)
A16: 46376 | B16: =$A16+6 | C16: =SUMIFS('작업 Jobs'!$H$3:$H$1002,'작업 Jobs'!$C$3:$C$1002,">="&$A16,'작업 Jobs'!$C$3:$C$1002,"<="&$B16) | D16: =SUMIFS('지출 Expenses'!$D$3:$D$1002,'지출 Expenses'!$A$3:$A$1002,">="&$A16,'지출 Expenses'!$A$3:$A$1002,"<="&$B16) | E16: =$C16-$D16 | F16: =IF(OR('설정 Settings'!$C$39="NO",$A16<'설정 Settings'!$C$41),"-","A") | G16: =IF($E16<=0,0,'설정 Settings'!$C$44*MIN($E16,$R$6)+MAX(0,$E16-$R$6)) | H16: =IF($F16="A",MAX(0,$R$4-$G16),0) | I16: =$H16+$E16 | J16: =$H16+$E16-MAX(0,$E16)*$R$7 | K16: =$E16-MAX(0,$E16)*$R$7 | L16: =IFERROR(($R$4-'설정 Settings'!$C$44*$E16+(1-$R$7)*$E16)/(1-$R$7),"") | Q16: EI 자격 | R16: ='설정 Settings'!$C$39 | S16: 설정 시트
A17: 46383 | B17: =$A17+6 | C17: =SUMIFS('작업 Jobs'!$H$3:$H$1002,'작업 Jobs'!$C$3:$C$1002,">="&$A17,'작업 Jobs'!$C$3:$C$1002,"<="&$B17) | D17: =SUMIFS('지출 Expenses'!$D$3:$D$1002,'지출 Expenses'!$A$3:$A$1002,">="&$A17,'지출 Expenses'!$A$3:$A$1002,"<="&$B17) | E17: =$C17-$D17 | F17: =IF(OR('설정 Settings'!$C$39="NO",$A17<'설정 Settings'!$C$41),"-","A") | G17: =IF($E17<=0,0,'설정 Settings'!$C$44*MIN($E17,$R$6)+MAX(0,$E17-$R$6)) | H17: =IF($F17="A",MAX(0,$R$4-$G17),0) | I17: =$H17+$E17 | J17: =$H17+$E17-MAX(0,$E17)*$R$7 | K17: =$E17-MAX(0,$E17)*$R$7 | L17: =IFERROR(($R$4-'설정 Settings'!$C$44*$E17+(1-$R$7)*$E17)/(1-$R$7),"")
A18: 46390 | B18: =$A18+6 | C18: =SUMIFS('작업 Jobs'!$H$3:$H$1002,'작업 Jobs'!$C$3:$C$1002,">="&$A18,'작업 Jobs'!$C$3:$C$1002,"<="&$B18) | D18: =SUMIFS('지출 Expenses'!$D$3:$D$1002,'지출 Expenses'!$A$3:$A$1002,">="&$A18,'지출 Expenses'!$A$3:$A$1002,"<="&$B18) | E18: =$C18-$D18 | F18: =IF(OR('설정 Settings'!$C$39="NO",$A18<'설정 Settings'!$C$41),"-","A") | G18: =IF($E18<=0,0,'설정 Settings'!$C$44*MIN($E18,$R$6)+MAX(0,$E18-$R$6)) | H18: =IF($F18="A",MAX(0,$R$4-$G18),0) | I18: =$H18+$E18 | J18: =$H18+$E18-MAX(0,$E18)*$R$7 | K18: =$E18-MAX(0,$E18)*$R$7 | L18: =IFERROR(($R$4-'설정 Settings'!$C$44*$E18+(1-$R$7)*$E18)/(1-$R$7),"")
A19: 46397 | B19: =$A19+6 | C19: =SUMIFS('작업 Jobs'!$H$3:$H$1002,'작업 Jobs'!$C$3:$C$1002,">="&$A19,'작업 Jobs'!$C$3:$C$1002,"<="&$B19) | D19: =SUMIFS('지출 Expenses'!$D$3:$D$1002,'지출 Expenses'!$A$3:$A$1002,">="&$A19,'지출 Expenses'!$A$3:$A$1002,"<="&$B19) | E19: =$C19-$D19 | F19: =IF(OR('설정 Settings'!$C$39="NO",$A19<'설정 Settings'!$C$41),"-","A") | G19: =IF($E19<=0,0,'설정 Settings'!$C$44*MIN($E19,$R$6)+MAX(0,$E19-$R$6)) | H19: =IF($F19="A",MAX(0,$R$4-$G19),0) | I19: =$H19+$E19 | J19: =$H19+$E19-MAX(0,$E19)*$R$7 | K19: =$E19-MAX(0,$E19)*$R$7 | L19: =IFERROR(($R$4-'설정 Settings'!$C$44*$E19+(1-$R$7)*$E19)/(1-$R$7),"")
A20: 46404 | B20: =$A20+6 | C20: =SUMIFS('작업 Jobs'!$H$3:$H$1002,'작업 Jobs'!$C$3:$C$1002,">="&$A20,'작업 Jobs'!$C$3:$C$1002,"<="&$B20) | D20: =SUMIFS('지출 Expenses'!$D$3:$D$1002,'지출 Expenses'!$A$3:$A$1002,">="&$A20,'지출 Expenses'!$A$3:$A$1002,"<="&$B20) | E20: =$C20-$D20 | F20: =IF(OR('설정 Settings'!$C$39="NO",$A20<'설정 Settings'!$C$41),"-","A") | G20: =IF($E20<=0,0,'설정 Settings'!$C$44*MIN($E20,$R$6)+MAX(0,$E20-$R$6)) | H20: =IF($F20="A",MAX(0,$R$4-$G20),0) | I20: =$H20+$E20 | J20: =$H20+$E20-MAX(0,$E20)*$R$7 | K20: =$E20-MAX(0,$E20)*$R$7 | L20: =IFERROR(($R$4-'설정 Settings'!$C$44*$E20+(1-$R$7)*$E20)/(1-$R$7),"")
A21: 46411 | B21: =$A21+6 | C21: =SUMIFS('작업 Jobs'!$H$3:$H$1002,'작업 Jobs'!$C$3:$C$1002,">="&$A21,'작업 Jobs'!$C$3:$C$1002,"<="&$B21) | D21: =SUMIFS('지출 Expenses'!$D$3:$D$1002,'지출 Expenses'!$A$3:$A$1002,">="&$A21,'지출 Expenses'!$A$3:$A$1002,"<="&$B21) | E21: =$C21-$D21 | F21: =IF(OR('설정 Settings'!$C$39="NO",$A21<'설정 Settings'!$C$41),"-","A") | G21: =IF($E21<=0,0,'설정 Settings'!$C$44*MIN($E21,$R$6)+MAX(0,$E21-$R$6)) | H21: =IF($F21="A",MAX(0,$R$4-$G21),0) | I21: =$H21+$E21 | J21: =$H21+$E21-MAX(0,$E21)*$R$7 | K21: =$E21-MAX(0,$E21)*$R$7 | L21: =IFERROR(($R$4-'설정 Settings'!$C$44*$E21+(1-$R$7)*$E21)/(1-$R$7),"")
A22: 46418 | B22: =$A22+6 | C22: =SUMIFS('작업 Jobs'!$H$3:$H$1002,'작업 Jobs'!$C$3:$C$1002,">="&$A22,'작업 Jobs'!$C$3:$C$1002,"<="&$B22) | D22: =SUMIFS('지출 Expenses'!$D$3:$D$1002,'지출 Expenses'!$A$3:$A$1002,">="&$A22,'지출 Expenses'!$A$3:$A$1002,"<="&$B22) | E22: =$C22-$D22 | F22: =IF(OR('설정 Settings'!$C$39="NO",$A22<'설정 Settings'!$C$41),"-","A") | G22: =IF($E22<=0,0,'설정 Settings'!$C$44*MIN($E22,$R$6)+MAX(0,$E22-$R$6)) | H22: =IF($F22="A",MAX(0,$R$4-$G22),0) | I22: =$H22+$E22 | J22: =$H22+$E22-MAX(0,$E22)*$R$7 | K22: =$E22-MAX(0,$E22)*$R$7 | L22: =IFERROR(($R$4-'설정 Settings'!$C$44*$E22+(1-$R$7)*$E22)/(1-$R$7),"")
A23: 46425 | B23: =$A23+6 | C23: =SUMIFS('작업 Jobs'!$H$3:$H$1002,'작업 Jobs'!$C$3:$C$1002,">="&$A23,'작업 Jobs'!$C$3:$C$1002,"<="&$B23) | D23: =SUMIFS('지출 Expenses'!$D$3:$D$1002,'지출 Expenses'!$A$3:$A$1002,">="&$A23,'지출 Expenses'!$A$3:$A$1002,"<="&$B23) | E23: =$C23-$D23 | F23: =IF(OR('설정 Settings'!$C$39="NO",$A23<'설정 Settings'!$C$41),"-","A") | G23: =IF($E23<=0,0,'설정 Settings'!$C$44*MIN($E23,$R$6)+MAX(0,$E23-$R$6)) | H23: =IF($F23="A",MAX(0,$R$4-$G23),0) | I23: =$H23+$E23 | J23: =$H23+$E23-MAX(0,$E23)*$R$7 | K23: =$E23-MAX(0,$E23)*$R$7 | L23: =IFERROR(($R$4-'설정 Settings'!$C$44*$E23+(1-$R$7)*$E23)/(1-$R$7),"")
A24: 46432 | B24: =$A24+6 | C24: =SUMIFS('작업 Jobs'!$H$3:$H$1002,'작업 Jobs'!$C$3:$C$1002,">="&$A24,'작업 Jobs'!$C$3:$C$1002,"<="&$B24) | D24: =SUMIFS('지출 Expenses'!$D$3:$D$1002,'지출 Expenses'!$A$3:$A$1002,">="&$A24,'지출 Expenses'!$A$3:$A$1002,"<="&$B24) | E24: =$C24-$D24 | F24: =IF(OR('설정 Settings'!$C$39="NO",$A24<'설정 Settings'!$C$41),"-","A") | G24: =IF($E24<=0,0,'설정 Settings'!$C$44*MIN($E24,$R$6)+MAX(0,$E24-$R$6)) | H24: =IF($F24="A",MAX(0,$R$4-$G24),0) | I24: =$H24+$E24 | J24: =$H24+$E24-MAX(0,$E24)*$R$7 | K24: =$E24-MAX(0,$E24)*$R$7 | L24: =IFERROR(($R$4-'설정 Settings'!$C$44*$E24+(1-$R$7)*$E24)/(1-$R$7),"")
A25: 46439 | B25: =$A25+6 | C25: =SUMIFS('작업 Jobs'!$H$3:$H$1002,'작업 Jobs'!$C$3:$C$1002,">="&$A25,'작업 Jobs'!$C$3:$C$1002,"<="&$B25) | D25: =SUMIFS('지출 Expenses'!$D$3:$D$1002,'지출 Expenses'!$A$3:$A$1002,">="&$A25,'지출 Expenses'!$A$3:$A$1002,"<="&$B25) | E25: =$C25-$D25 | F25: =IF(OR('설정 Settings'!$C$39="NO",$A25<'설정 Settings'!$C$41),"-","A") | G25: =IF($E25<=0,0,'설정 Settings'!$C$44*MIN($E25,$R$6)+MAX(0,$E25-$R$6)) | H25: =IF($F25="A",MAX(0,$R$4-$G25),0) | I25: =$H25+$E25 | J25: =$H25+$E25-MAX(0,$E25)*$R$7 | K25: =$E25-MAX(0,$E25)*$R$7 | L25: =IFERROR(($R$4-'설정 Settings'!$C$44*$E25+(1-$R$7)*$E25)/(1-$R$7),"")
A26: 46446 | B26: =$A26+6 | C26: =SUMIFS('작업 Jobs'!$H$3:$H$1002,'작업 Jobs'!$C$3:$C$1002,">="&$A26,'작업 Jobs'!$C$3:$C$1002,"<="&$B26) | D26: =SUMIFS('지출 Expenses'!$D$3:$D$1002,'지출 Expenses'!$A$3:$A$1002,">="&$A26,'지출 Expenses'!$A$3:$A$1002,"<="&$B26) | E26: =$C26-$D26 | F26: =IF(OR('설정 Settings'!$C$39="NO",$A26<'설정 Settings'!$C$41),"-","A") | G26: =IF($E26<=0,0,'설정 Settings'!$C$44*MIN($E26,$R$6)+MAX(0,$E26-$R$6)) | H26: =IF($F26="A",MAX(0,$R$4-$G26),0) | I26: =$H26+$E26 | J26: =$H26+$E26-MAX(0,$E26)*$R$7 | K26: =$E26-MAX(0,$E26)*$R$7 | L26: =IFERROR(($R$4-'설정 Settings'!$C$44*$E26+(1-$R$7)*$E26)/(1-$R$7),"")
A27: 46453 | B27: =$A27+6 | C27: =SUMIFS('작업 Jobs'!$H$3:$H$1002,'작업 Jobs'!$C$3:$C$1002,">="&$A27,'작업 Jobs'!$C$3:$C$1002,"<="&$B27) | D27: =SUMIFS('지출 Expenses'!$D$3:$D$1002,'지출 Expenses'!$A$3:$A$1002,">="&$A27,'지출 Expenses'!$A$3:$A$1002,"<="&$B27) | E27: =$C27-$D27 | F27: =IF(OR('설정 Settings'!$C$39="NO",$A27<'설정 Settings'!$C$41),"-","A") | G27: =IF($E27<=0,0,'설정 Settings'!$C$44*MIN($E27,$R$6)+MAX(0,$E27-$R$6)) | H27: =IF($F27="A",MAX(0,$R$4-$G27),0) | I27: =$H27+$E27 | J27: =$H27+$E27-MAX(0,$E27)*$R$7 | K27: =$E27-MAX(0,$E27)*$R$7 | L27: =IFERROR(($R$4-'설정 Settings'!$C$44*$E27+(1-$R$7)*$E27)/(1-$R$7),"")
A28: 46460 | B28: =$A28+6 | C28: =SUMIFS('작업 Jobs'!$H$3:$H$1002,'작업 Jobs'!$C$3:$C$1002,">="&$A28,'작업 Jobs'!$C$3:$C$1002,"<="&$B28) | D28: =SUMIFS('지출 Expenses'!$D$3:$D$1002,'지출 Expenses'!$A$3:$A$1002,">="&$A28,'지출 Expenses'!$A$3:$A$1002,"<="&$B28) | E28: =$C28-$D28 | F28: =IF(OR('설정 Settings'!$C$39="NO",$A28<'설정 Settings'!$C$41),"-","A") | G28: =IF($E28<=0,0,'설정 Settings'!$C$44*MIN($E28,$R$6)+MAX(0,$E28-$R$6)) | H28: =IF($F28="A",MAX(0,$R$4-$G28),0) | I28: =$H28+$E28 | J28: =$H28+$E28-MAX(0,$E28)*$R$7 | K28: =$E28-MAX(0,$E28)*$R$7 | L28: =IFERROR(($R$4-'설정 Settings'!$C$44*$E28+(1-$R$7)*$E28)/(1-$R$7),"")
... A34: 46502 | B34: =$A34+6 | C34: =SUMIFS('작업 Jobs'!$H$3:$H$1002,'작업 Jobs'!$C$3:$C$1002,">="&$A34,'작업 Jobs'!$C$3:$C$1002,"<="&$B34) | D34: =SUMIFS('지출 Expenses'!$D$3:$D$1002,'지출 Expenses'!$A$3:$A$1002,">="&$A34,'지출 Expenses'!$A$3:$A$1002,"<="&$B34) | E34: =$C34-$D34 | F34: =IF(OR('설정 Settings'!$C$39="NO",$A34<'설정 Settings'!$C$41),"-","A") | G34: =IF($E34<=0,0,'설정 Settings'!$C$44*MIN($E34,$R$6)+MAX(0,$E34-$R$6)) | H34: =IF($F34="A",MAX(0,$R$4-$G34),0) | I34: =$H34+$E34 | J34: =$H34+$E34-MAX(0,$E34)*$R$7 | K34: =$E34-MAX(0,$E34)*$R$7 | L34: =IFERROR(($R$4-'설정 Settings'!$C$44*$E34+(1-$R$7)*$E34)/(1-$R$7),"")

Sheet 세금 Tax
A1: 세금 Tax — GST/HST 분기 점검, CPP 적립, T2125 분류 (세무 자문 아님)
A2: 매출은 작업 시트의 완료일 기준, 지출은 지출 시트 기준입니다. 입금 시트와의 차이는 미수금·입금 시기 때문입니다. 소규모 사업자 기준 $30,000: 4분기 합계 테스트 + 단일 분기 테스트 (ETA s.148, F7). 경고선: 4분기 $25,000, 단일 분기 $20,000 (memo §10 item 15).
A4: 분기 Quarter | B4: 시작 | C4: 끝 | D4: 총매출 Gross (Jobs) | E4: 과세매출 (테스트) Taxable (test) | F4: 4분기 합계 Rolling 4Q | G4: 단일 분기 경고 Single-quarter | H4: 4분기 경고 Rolling flag | I4: 입금 합계 Payments | J4: 차이 Diff | K4: 지출 Expenses | L4: 순이익 Net | M4: CPP 적립 11.9% Set aside
A5: 2026 Q3 | B5: 46204 | C5: 46295 | D5: =SUMIFS('작업 Jobs'!$H$3:$H$1002,'작업 Jobs'!$C$3:$C$1002,">="&$B5,'작업 Jobs'!$C$3:$C$1002,"<="&$C5) | E5: =$D5-IF('설정 Settings'!$C$31="NO",SUMIFS('작업 Jobs'!$H$3:$H$1002,'작업 Jobs'!$F$3:$F$1002,"PLAT",'작업 Jobs'!$C$3:$C$1002,">="&$B5,'작업 Jobs'!$C$3:$C$1002,"<="&$C5),0) | F5: =SUM($E$5:$E5) | G5: =IF($E5>'설정 Settings'!$C$28,"기준 이상 — 단일 분기 테스트: 등록 확인",IF($E5>='설정 Settings'!$C$30,"경고: 단일 분기 경고선 이상","")) | H5: =IF($F5>'설정 Settings'!$C$28,"기준 초과 — 등록 준비 (분기+다음 달까지 소규모 지위, F7)",IF($F5>='설정 Settings'!$C$29,"경고: 4분기 합계 경고선 이상","")) | I5: =SUMIFS('입금 Payments'!$C$3:$C$1002,'입금 Payments'!$A$3:$A$1002,">="&$B5,'입금 Payments'!$A$3:$A$1002,"<="&$C5) | J5: =$D5-$I5 | K5: =SUMIFS('지출 Expenses'!$D$3:$D$1002,'지출 Expenses'!$A$3:$A$1002,">="&$B5,'지출 Expenses'!$A$3:$A$1002,"<="&$C5) | L5: =$D5-$K5 | M5: =MAX(0,$L5)*'설정 Settings'!$C$32
A6: 2026 Q4 | B6: 46296 | C6: 46387 | D6: =SUMIFS('작업 Jobs'!$H$3:$H$1002,'작업 Jobs'!$C$3:$C$1002,">="&$B6,'작업 Jobs'!$C$3:$C$1002,"<="&$C6) | E6: =$D6-IF('설정 Settings'!$C$31="NO",SUMIFS('작업 Jobs'!$H$3:$H$1002,'작업 Jobs'!$F$3:$F$1002,"PLAT",'작업 Jobs'!$C$3:$C$1002,">="&$B6,'작업 Jobs'!$C$3:$C$1002,"<="&$C6),0) | F6: =SUM($E$5:$E6) | G6: =IF($E6>'설정 Settings'!$C$28,"기준 이상 — 단일 분기 테스트: 등록 확인",IF($E6>='설정 Settings'!$C$30,"경고: 단일 분기 경고선 이상","")) | H6: =IF($F6>'설정 Settings'!$C$28,"기준 초과 — 등록 준비 (분기+다음 달까지 소규모 지위, F7)",IF($F6>='설정 Settings'!$C$29,"경고: 4분기 합계 경고선 이상","")) | I6: =SUMIFS('입금 Payments'!$C$3:$C$1002,'입금 Payments'!$A$3:$A$1002,">="&$B6,'입금 Payments'!$A$3:$A$1002,"<="&$C6) | J6: =$D6-$I6 | K6: =SUMIFS('지출 Expenses'!$D$3:$D$1002,'지출 Expenses'!$A$3:$A$1002,">="&$B6,'지출 Expenses'!$A$3:$A$1002,"<="&$C6) | L6: =$D6-$K6 | M6: =MAX(0,$L6)*'설정 Settings'!$C$32
A7: 2027 Q1 | B7: 46388 | C7: 46477 | D7: =SUMIFS('작업 Jobs'!$H$3:$H$1002,'작업 Jobs'!$C$3:$C$1002,">="&$B7,'작업 Jobs'!$C$3:$C$1002,"<="&$C7) | E7: =$D7-IF('설정 Settings'!$C$31="NO",SUMIFS('작업 Jobs'!$H$3:$H$1002,'작업 Jobs'!$F$3:$F$1002,"PLAT",'작업 Jobs'!$C$3:$C$1002,">="&$B7,'작업 Jobs'!$C$3:$C$1002,"<="&$C7),0) | F7: =SUM($E$5:$E7) | G7: =IF($E7>'설정 Settings'!$C$28,"기준 이상 — 단일 분기 테스트: 등록 확인",IF($E7>='설정 Settings'!$C$30,"경고: 단일 분기 경고선 이상","")) | H7: =IF($F7>'설정 Settings'!$C$28,"기준 초과 — 등록 준비 (분기+다음 달까지 소규모 지위, F7)",IF($F7>='설정 Settings'!$C$29,"경고: 4분기 합계 경고선 이상","")) | I7: =SUMIFS('입금 Payments'!$C$3:$C$1002,'입금 Payments'!$A$3:$A$1002,">="&$B7,'입금 Payments'!$A$3:$A$1002,"<="&$C7) | J7: =$D7-$I7 | K7: =SUMIFS('지출 Expenses'!$D$3:$D$1002,'지출 Expenses'!$A$3:$A$1002,">="&$B7,'지출 Expenses'!$A$3:$A$1002,"<="&$C7) | L7: =$D7-$K7 | M7: =MAX(0,$L7)*'설정 Settings'!$C$32
A8: 2027 Q2 | B8: 46478 | C8: 46568 | D8: =SUMIFS('작업 Jobs'!$H$3:$H$1002,'작업 Jobs'!$C$3:$C$1002,">="&$B8,'작업 Jobs'!$C$3:$C$1002,"<="&$C8) | E8: =$D8-IF('설정 Settings'!$C$31="NO",SUMIFS('작업 Jobs'!$H$3:$H$1002,'작업 Jobs'!$F$3:$F$1002,"PLAT",'작업 Jobs'!$C$3:$C$1002,">="&$B8,'작업 Jobs'!$C$3:$C$1002,"<="&$C8),0) | F8: =SUM($E$5:$E8) | G8: =IF($E8>'설정 Settings'!$C$28,"기준 이상 — 단일 분기 테스트: 등록 확인",IF($E8>='설정 Settings'!$C$30,"경고: 단일 분기 경고선 이상","")) | H8: =IF($F8>'설정 Settings'!$C$28,"기준 초과 — 등록 준비 (분기+다음 달까지 소규모 지위, F7)",IF($F8>='설정 Settings'!$C$29,"경고: 4분기 합계 경고선 이상","")) | I8: =SUMIFS('입금 Payments'!$C$3:$C$1002,'입금 Payments'!$A$3:$A$1002,">="&$B8,'입금 Payments'!$A$3:$A$1002,"<="&$C8) | J8: =$D8-$I8 | K8: =SUMIFS('지출 Expenses'!$D$3:$D$1002,'지출 Expenses'!$A$3:$A$1002,">="&$B8,'지출 Expenses'!$A$3:$A$1002,"<="&$C8) | L8: =$D8-$K8 | M8: =MAX(0,$L8)*'설정 Settings'!$C$32
A9: 2027 Q3 | B9: 46569 | C9: 46660 | D9: =SUMIFS('작업 Jobs'!$H$3:$H$1002,'작업 Jobs'!$C$3:$C$1002,">="&$B9,'작업 Jobs'!$C$3:$C$1002,"<="&$C9) | E9: =$D9-IF('설정 Settings'!$C$31="NO",SUMIFS('작업 Jobs'!$H$3:$H$1002,'작업 Jobs'!$F$3:$F$1002,"PLAT",'작업 Jobs'!$C$3:$C$1002,">="&$B9,'작업 Jobs'!$C$3:$C$1002,"<="&$C9),0) | F9: =SUM($E$6:$E9) | G9: =IF($E9>'설정 Settings'!$C$28,"기준 이상 — 단일 분기 테스트: 등록 확인",IF($E9>='설정 Settings'!$C$30,"경고: 단일 분기 경고선 이상","")) | H9: =IF($F9>'설정 Settings'!$C$28,"기준 초과 — 등록 준비 (분기+다음 달까지 소규모 지위, F7)",IF($F9>='설정 Settings'!$C$29,"경고: 4분기 합계 경고선 이상","")) | I9: =SUMIFS('입금 Payments'!$C$3:$C$1002,'입금 Payments'!$A$3:$A$1002,">="&$B9,'입금 Payments'!$A$3:$A$1002,"<="&$C9) | J9: =$D9-$I9 | K9: =SUMIFS('지출 Expenses'!$D$3:$D$1002,'지출 Expenses'!$A$3:$A$1002,">="&$B9,'지출 Expenses'!$A$3:$A$1002,"<="&$C9) | L9: =$D9-$K9 | M9: =MAX(0,$L9)*'설정 Settings'!$C$32
A10: 2027 Q4 | B10: 46661 | C10: 46752 | D10: =SUMIFS('작업 Jobs'!$H$3:$H$1002,'작업 Jobs'!$C$3:$C$1002,">="&$B10,'작업 Jobs'!$C$3:$C$1002,"<="&$C10) | E10: =$D10-IF('설정 Settings'!$C$31="NO",SUMIFS('작업 Jobs'!$H$3:$H$1002,'작업 Jobs'!$F$3:$F$1002,"PLAT",'작업 Jobs'!$C$3:$C$1002,">="&$B10,'작업 Jobs'!$C$3:$C$1002,"<="&$C10),0) | F10: =SUM($E$7:$E10) | G10: =IF($E10>'설정 Settings'!$C$28,"기준 이상 — 단일 분기 테스트: 등록 확인",IF($E10>='설정 Settings'!$C$30,"경고: 단일 분기 경고선 이상","")) | H10: =IF($F10>'설정 Settings'!$C$28,"기준 초과 — 등록 준비 (분기+다음 달까지 소규모 지위, F7)",IF($F10>='설정 Settings'!$C$29,"경고: 4분기 합계 경고선 이상","")) | I10: =SUMIFS('입금 Payments'!$C$3:$C$1002,'입금 Payments'!$A$3:$A$1002,">="&$B10,'입금 Payments'!$A$3:$A$1002,"<="&$C10) | J10: =$D10-$I10 | K10: =SUMIFS('지출 Expenses'!$D$3:$D$1002,'지출 Expenses'!$A$3:$A$1002,">="&$B10,'지출 Expenses'!$A$3:$A$1002,"<="&$C10) | L10: =$D10-$K10 | M10: =MAX(0,$L10)*'설정 Settings'!$C$32
A11: 2028 Q1 | B11: 46753 | C11: 46843 | D11: =SUMIFS('작업 Jobs'!$H$3:$H$1002,'작업 Jobs'!$C$3:$C$1002,">="&$B11,'작업 Jobs'!$C$3:$C$1002,"<="&$C11) | E11: =$D11-IF('설정 Settings'!$C$31="NO",SUMIFS('작업 Jobs'!$H$3:$H$1002,'작업 Jobs'!$F$3:$F$1002,"PLAT",'작업 Jobs'!$C$3:$C$1002,">="&$B11,'작업 Jobs'!$C$3:$C$1002,"<="&$C11),0) | F11: =SUM($E$8:$E11) | G11: =IF($E11>'설정 Settings'!$C$28,"기준 이상 — 단일 분기 테스트: 등록 확인",IF($E11>='설정 Settings'!$C$30,"경고: 단일 분기 경고선 이상","")) | H11: =IF($F11>'설정 Settings'!$C$28,"기준 초과 — 등록 준비 (분기+다음 달까지 소규모 지위, F7)",IF($F11>='설정 Settings'!$C$29,"경고: 4분기 합계 경고선 이상","")) | I11: =SUMIFS('입금 Payments'!$C$3:$C$1002,'입금 Payments'!$A$3:$A$1002,">="&$B11,'입금 Payments'!$A$3:$A$1002,"<="&$C11) | J11: =$D11-$I11 | K11: =SUMIFS('지출 Expenses'!$D$3:$D$1002,'지출 Expenses'!$A$3:$A$1002,">="&$B11,'지출 Expenses'!$A$3:$A$1002,"<="&$C11) | L11: =$D11-$K11 | M11: =MAX(0,$L11)*'설정 Settings'!$C$32
A12: 2028 Q2 | B12: 46844 | C12: 46934 | D12: =SUMIFS('작업 Jobs'!$H$3:$H$1002,'작업 Jobs'!$C$3:$C$1002,">="&$B12,'작업 Jobs'!$C$3:$C$1002,"<="&$C12) | E12: =$D12-IF('설정 Settings'!$C$31="NO",SUMIFS('작업 Jobs'!$H$3:$H$1002,'작업 Jobs'!$F$3:$F$1002,"PLAT",'작업 Jobs'!$C$3:$C$1002,">="&$B12,'작업 Jobs'!$C$3:$C$1002,"<="&$C12),0) | F12: =SUM($E$9:$E12) | G12: =IF($E12>'설정 Settings'!$C$28,"기준 이상 — 단일 분기 테스트: 등록 확인",IF($E12>='설정 Settings'!$C$30,"경고: 단일 분기 경고선 이상","")) | H12: =IF($F12>'설정 Settings'!$C$28,"기준 초과 — 등록 준비 (분기+다음 달까지 소규모 지위, F7)",IF($F12>='설정 Settings'!$C$29,"경고: 4분기 합계 경고선 이상","")) | I12: =SUMIFS('입금 Payments'!$C$3:$C$1002,'입금 Payments'!$A$3:$A$1002,">="&$B12,'입금 Payments'!$A$3:$A$1002,"<="&$C12) | J12: =$D12-$I12 | K12: =SUMIFS('지출 Expenses'!$D$3:$D$1002,'지출 Expenses'!$A$3:$A$1002,">="&$B12,'지출 Expenses'!$A$3:$A$1002,"<="&$C12) | L12: =$D12-$K12 | M12: =MAX(0,$L12)*'설정 Settings'!$C$32
A13: 4분기 합계: 첫 분기들은 그 전 분기가 없으므로 있는 분기만 더합니다. 하나의 분기가 $30,000을 넘으면 그 공급부터 등록 대상일 수 있음 (단일 분기 테스트) — 확인 필요. 등록 전에는 인보이스에 세금을 넣지 않습니다.
A15: 연도별 요약 Annual summary
A16: 연도 Year | B16: 총매출 | C16: 지출 | D16: 순이익 | E16: CPP 적립 (11.9% × 순이익) | F16: CPP 추정 (기본공제 반영) | G16: 주행 km | H16: 비고
A17: 2026 | B17: =SUMIFS('작업 Jobs'!$H$3:$H$1002,'작업 Jobs'!$C$3:$C$1002,">="&DATE($A17,1,1),'작업 Jobs'!$C$3:$C$1002,"<="&DATE($A17,12,31)) | C17: =SUMIFS('지출 Expenses'!$D$3:$D$1002,'지출 Expenses'!$A$3:$A$1002,">="&DATE($A17,1,1),'지출 Expenses'!$A$3:$A$1002,"<="&DATE($A17,12,31)) | D17: =$B17-$C17 | E17: =MAX(0,$D17)*'설정 Settings'!$C$32 | F17: =MAX(0,$D17-'설정 Settings'!$C$33)*'설정 Settings'!$C$32 | G17: =SUMIFS('주행 Mileage'!$F$3:$F$1002,'주행 Mileage'!$A$3:$A$1002,">="&DATE($A17,1,1),'주행 Mileage'!$A$3:$A$1002,"<="&DATE($A17,12,31)) | H17: 적립은 보수적인 E열 권장 (memo 5.4는 기본공제를 무시)
A18: 2027 | B18: =SUMIFS('작업 Jobs'!$H$3:$H$1002,'작업 Jobs'!$C$3:$C$1002,">="&DATE($A18,1,1),'작업 Jobs'!$C$3:$C$1002,"<="&DATE($A18,12,31)) | C18: =SUMIFS('지출 Expenses'!$D$3:$D$1002,'지출 Expenses'!$A$3:$A$1002,">="&DATE($A18,1,1),'지출 Expenses'!$A$3:$A$1002,"<="&DATE($A18,12,31)) | D18: =$B18-$C18 | E18: =MAX(0,$D18)*'설정 Settings'!$C$32 | F18: =MAX(0,$D18-'설정 Settings'!$C$33)*'설정 Settings'!$C$32 | G18: =SUMIFS('주행 Mileage'!$F$3:$F$1002,'주행 Mileage'!$A$3:$A$1002,">="&DATE($A18,1,1),'주행 Mileage'!$A$3:$A$1002,"<="&DATE($A18,12,31))
A20: 마감·규칙 Deadlines & rules (memo §6)
A21: 소득세: T1 + T2125. 2026년분은 2027-06-15까지 신고, 2027-04-30까지 납부 (memo §6). | H21: https://github.com/justicecanada/laws-lois-xml/blob/main/eng/acts/I-3.3.xml
A22: 분납(instalments): 올해 또는 지난 2년 각각의 순 세금이 $3,000 이하면 필요 없음 (ITA s.156.1(1),(2)(b), F10). 본인 해당 여부는 추정 — 확인 필요. | H22: https://github.com/justicecanada/laws-lois-xml/blob/main/eng/acts/I-3.3.xml
A23: CPP: 자영업 9.9% + 2.0% = 11.9%, 기본공제 $3,500 초과분 (F9). 적립은 순이익 전체의 11.9%로 보수적으로. | H23: https://github.com/justicecanada/laws-lois-xml/blob/main/eng/acts/C-8.xml
A24: GST/HST: 온타리오 HST 13% (ETA s.165, Sched. VIII, F8). 자발적 등록은 1년간 취소 불가 (ETA s.242(2), F8) → B2C는 기준 전까지 미등록 유지 (memo §6). | H24: https://github.com/justicecanada/laws-lois-xml/blob/main/eng/acts/E-15.xml
A25: 플랫폼(TaskRabbit·Jiffy) 수입이 본인 과세매출인지 확인 안 됨 (memo 5.5) — 설정 시트 스위치로 조정. | H25: business/research/decision-memo.md
A26: 소득세율·소득세 적립액은 연구 범위 밖이라 이 시트에 없습니다. 회계사 또는 CRA에 확인.
A29: T2125 지출 분류 — 확인 필요: 연구 자료에 없는 목록입니다. 최신 CRA T2125 양식에서 줄 번호·이름을 확인하세요
A30: 분류 Category (지출 시트 목록) | B30: 한국어 | C30: 예시·주의 (확인 필요) | D30: 합계 (전체 기간)
A31: 8521 Advertising | B31: 광고 | C31: 문고리 광고지·전단 인쇄, 유료 광고 | D31: =SUMIFS('지출 Expenses'!$D$3:$D$1002,'지출 Expenses'!$E$3:$E$1002,$A31)
A32: 8523 Meals and entertainment | B32: 식대·접대 | C32: 공제 한도 규정 확인 필요 | D32: =SUMIFS('지출 Expenses'!$D$3:$D$1002,'지출 Expenses'!$E$3:$E$1002,$A32)
A33: 8590 Bad debts | B33: 대손 (못 받은 돈) | D33: =SUMIFS('지출 Expenses'!$D$3:$D$1002,'지출 Expenses'!$E$3:$E$1002,$A33)
A34: 8690 Insurance | B34: 보험 | C34: 청소 CGL, 사다리·제설 보험 | D34: =SUMIFS('지출 Expenses'!$D$3:$D$1002,'지출 Expenses'!$E$3:$E$1002,$A34)
A35: 8710 Interest and bank charges | B35: 이자·은행 수수료 | C35: 카드 결제 수수료 분류 확인 필요 | D35: =SUMIFS('지출 Expenses'!$D$3:$D$1002,'지출 Expenses'!$E$3:$E$1002,$A35)
A36: 8760 Business taxes, licences and memberships | B36: 사업세·면허·회비 | C36: 플랫폼 가입비($25) 분류 확인 필요 | D36: =SUMIFS('지출 Expenses'!$D$3:$D$1002,'지출 Expenses'!$E$3:$E$1002,$A36)
A37: 8810 Office expenses | B37: 사무 비용 | D37: =SUMIFS('지출 Expenses'!$D$3:$D$1002,'지출 Expenses'!$E$3:$E$1002,$A37)
A38: 8811 Office stationery and supplies | B38: 사무용품·소모품 | C38: 청소 용품 분류는 확인 필요 | D38: =SUMIFS('지출 Expenses'!$D$3:$D$1002,'지출 Expenses'!$E$3:$E$1002,$A38)
A39: 8860 Professional fees | B39: 전문가 수수료 (회계·법률) | D39: =SUMIFS('지출 Expenses'!$D$3:$D$1002,'지출 Expenses'!$E$3:$E$1002,$A39)
A40: 8871 Management and administration fees | B40: 관리·행정 수수료 | D40: =SUMIFS('지출 Expenses'!$D$3:$D$1002,'지출 Expenses'!$E$3:$E$1002,$A40)
A41: 8910 Rent | B41: 임차료 | D41: =SUMIFS('지출 Expenses'!$D$3:$D$1002,'지출 Expenses'!$E$3:$E$1002,$A41)
A42: 8960 Repairs and maintenance | B42: 수리·유지보수 | D42: =SUMIFS('지출 Expenses'!$D$3:$D$1002,'지출 Expenses'!$E$3:$E$1002,$A42)
A43: 9060 Salaries, wages and benefits | B43: 급여 | C43: 첫 달에는 고용 없음 (memo §3) | D43: =SUMIFS('지출 Expenses'!$D$3:$D$1002,'지출 Expenses'!$E$3:$E$1002,$A43)
A44: 9180 Property taxes | B44: 재산세 | D44: =SUMIFS('지출 Expenses'!$D$3:$D$1002,'지출 Expenses'!$E$3:$E$1002,$A44)
A45: 9200 Travel expenses | B45: 출장·여행 | D45: =SUMIFS('지출 Expenses'!$D$3:$D$1002,'지출 Expenses'!$E$3:$E$1002,$A45)
A46: 9220 Utilities | B46: 공과금 | C46: 휴대폰 요금 분류 확인 필요 | D46: =SUMIFS('지출 Expenses'!$D$3:$D$1002,'지출 Expenses'!$E$3:$E$1002,$A46)
A47: 9224 Fuel costs (except for motor vehicles) | B47: 연료 (차량 제외) | C47: 제설기 연료 등 | D47: =SUMIFS('지출 Expenses'!$D$3:$D$1002,'지출 Expenses'!$E$3:$E$1002,$A47)
A48: 9275 Delivery, freight and express | B48: 배송·운송 | D48: =SUMIFS('지출 Expenses'!$D$3:$D$1002,'지출 Expenses'!$E$3:$E$1002,$A48)
A49: 9281 Motor vehicle expenses (not including CCA) | B49: 차량 비용 (감가상각 제외) | C49: 주행 시트 기록 필요 | D49: =SUMIFS('지출 Expenses'!$D$3:$D$1002,'지출 Expenses'!$E$3:$E$1002,$A49)
A50: 9936 Capital cost allowance (CCA) | B50: 감가상각 (CCA) | C50: 사다리·제설기 등 — 확인 필요 | D50: =SUMIFS('지출 Expenses'!$D$3:$D$1002,'지출 Expenses'!$E$3:$E$1002,$A50)
A51: 9945 Business-use-of-home expenses | B51: 자택 사업 사용분 | D51: =SUMIFS('지출 Expenses'!$D$3:$D$1002,'지출 Expenses'!$E$3:$E$1002,$A51)
A52: 9270 Other expenses | B52: 기타 비용 | D52: =SUMIFS('지출 Expenses'!$D$3:$D$1002,'지출 Expenses'!$E$3:$E$1002,$A52)
A53: 미분류 Not sure | B53: 미분류 | C53: 회계사에게 확인 | D53: =SUMIFS('지출 Expenses'!$D$3:$D$1002,'지출 Expenses'!$E$3:$E$1002,$A53)

Sheet 손익분기 Break-even
A1: 손익분기 Break-even (memo 5.3) — 추정, 첫 시즌 기준
A2: 기본·보수 열은 memo 5.3 가정입니다. 실제 열은 설정 시트의 실제 견적과 견적 시트에서 성사(WON)된 가격 평균을 씁니다 (없으면 기본값). 제설기는 다음 시즌에도 쓸 수 있습니다.
A4: A. 홈통 청소 Gutters — G1 통과 후에만. 날짜 잡힌 예약 5건 전에는 사다리 사지 않기
A5: 항목 | B5: 기본 Base | C5: 보수 Conservative | D5: 실제 Actual | E5: 근거
A6: 설비비 Setup | B6: ='설정 Settings'!$C$73 | C6: ='설정 Settings'!$C$73 | D6: ='설정 Settings'!$C$73 | E6: 가정 A5 (보험 제외)
A7: 사다리·높이 보험 Ladder cover | B7: ='설정 Settings'!$C$74 | C7: ='설정 Settings'!$C$74 | D7: =IF('설정 Settings'!$C$75<>"",'설정 Settings'!$C$75,'설정 Settings'!$C$74) | E7: F27 하한 (SNIPPET). 실제 견적이 있으면 실제 열에 반영
A8: 고정비 합계 Fixed | B8: =$B$6+$B$7 | C8: =$C$6+$C$7 | D8: =$D$6+$D$7
A9: 작업당 가격 Ticket | B9: ='설정 Settings'!$C$76 | C9: ='설정 Settings'!$C$77 | D9: =IFERROR(AVERAGEIFS('견적 Quotes'!$H$3:$H$1002,'견적 Quotes'!$G$3:$G$1002,"GUT",'견적 Quotes'!$I$3:$I$1002,"WON"),'설정 Settings'!$C$76) | E9: 실제 = 성사된 홈통 견적 평균
A10: 작업당 변동비 Variable | B10: ='설정 Settings'!$C$68 | C10: ='설정 Settings'!$C$68 | D10: ='설정 Settings'!$C$68 | E10: 가정 A6
A11: 작업당 기여이익 Contribution | B11: =$B$9-$B$10 | C11: =$C$9-$C$10 | D11: =$D$9-$D$10 | E11: memo: 기본 $205, 보수 $155
A12: 손익분기 작업 수 Break-even jobs | B12: =ROUNDUP(IFERROR($B$8/$B$11,0),0) | C12: =ROUNDUP(IFERROR($C$8/$C$11,0),0) | D12: =ROUNDUP(IFERROR($D$8/$D$11,0),0) | E12: memo: 기본 10건, 보수 13건
A14: 성사된 홈통 작업 Signed (WON) | B14: =COUNTIFS('견적 Quotes'!$G$3:$G$1002,"GUT",'견적 Quotes'!$I$3:$I$1002,"WON") | C14: 견적 시트
A15: 날짜 잡힌 예약 Booked with dates | B15: =COUNTIFS('견적 Quotes'!$G$3:$G$1002,"GUT",'견적 Quotes'!$I$3:$I$1002,"WON",'견적 Quotes'!$K$3:$K$1002,"<>") | C15: G1 조건 5의 기준
A16: 완료된 홈통 작업 Completed | B16: =COUNTIFS('작업 Jobs'!$F$3:$F$1002,"GUT") | C16: 작업 시트
A17: 손익분기까지 남은 수 Remaining | B17: =MAX(0,$D$12-$B$14) | C17: 실제 열 기준
A18: 사다리 구매 규칙 Ladder rule | B18: =IF($B$15>='설정 Settings'!$C$95,"구매 가능 — 날짜 잡힌 예약 "&$B$15&"건","사다리 구매 금지 — 예약 "&$B$15&"/"&'설정 Settings'!$C$95) | C18: memo §2 G1 조건 5
A19: G1 상태 | B19: ='설정 Settings'!$C$94 | C19: 설정 시트
A21: B. 제설 Snow — Gate S(서면 보험) 후에만. 12/1 전 결제 없음, 11/20까지 손익분기 미달이면 모든 계약 무효
A22: 항목 | B22: 기본 Base | C22: 보수 Conservative | D22: 실제 Actual | E22: 근거
A23: 제설 보험 Snow cover | B23: ='설정 Settings'!$C$78 | C23: ='설정 Settings'!$C$79 | D23: =IF('설정 Settings'!$C$80<>"",'설정 Settings'!$C$80,'설정 Settings'!$C$78) | E23: F29 (SNIPPET)
A24: 제설기 Snowblower | B24: ='설정 Settings'!$C$81 | C24: ='설정 Settings'!$C$82 | D24: =IF('설정 Settings'!$C$83<>"",'설정 Settings'!$C$83,'설정 Settings'!$C$81) | E24: F30. 삽만 쓰면 0
A25: 시즌 가격 Season price | B25: ='설정 Settings'!$C$84 | C25: ='설정 Settings'!$C$85 | D25: =IFERROR(AVERAGEIFS('견적 Quotes'!$H$3:$H$1002,'견적 Quotes'!$G$3:$G$1002,"SNOW",'견적 Quotes'!$I$3:$I$1002,"WON"),'설정 Settings'!$C$84) | E25: 실제 = 성사된 제설 계약(SNOW) 시즌 총액 평균
A26: 직접비율 Direct cost % | B26: ='설정 Settings'!$C$67 | C26: ='설정 Settings'!$C$67 | D26: ='설정 Settings'!$C$67 | E26: 가정 A4
A27: 계약당 기여이익 Contribution | B27: =$B$25*(1-$B$26) | C27: =$C$25*(1-$C$26) | D27: =$D$25*(1-$D$26) | E27: memo: 기본 $425, 보수 $340
A28: 손익분기 — 제설기 With blower | B28: =ROUNDUP(IFERROR(($B$23+$B$24)/$B$27,0),0) | C28: =ROUNDUP(IFERROR(($C$23+$C$24)/$C$27,0),0) | D28: =ROUNDUP(IFERROR(($D$23+$D$24)/$D$27,0),0) | E28: memo: 기본 6, 보수 12
A29: 손익분기 — 삽만 Shovel only | B29: =ROUNDUP(IFERROR($B$23/$B$27,0),0) | C29: =ROUNDUP(IFERROR($C$23/$C$27,0),0) | D29: =ROUNDUP(IFERROR($D$23/$D$27,0),0) | E29: memo: 기본 3, 보수 6
A31: 제설 방식 Method | B31: ='설정 Settings'!$C$88 | C31: 설정 시트
A32: 적용 손익분기 (실제) Break-even used | B32: =IF($B$31="SHOVEL",$D$29,$D$28) | C32: 실제 열 + 제설 방식
A33: 서명한 제설 계약 Signed (WON) | B33: =COUNTIFS('견적 Quotes'!$G$3:$G$1002,"SNOW",'견적 Quotes'!$I$3:$I$1002,"WON") | C33: 견적 시트 (서비스 SNOW)
A34: 11/20까지 서명 Signed by deadline | B34: =COUNTIFS('견적 Quotes'!$G$3:$G$1002,"SNOW",'견적 Quotes'!$I$3:$I$1002,"WON",'견적 Quotes'!$J$3:$J$1002,"<="&'설정 Settings'!$C$106) | C34: 계약일 기준
A35: 남은 수 Remaining | B35: =MAX(0,$B$32-$B$34)
A36: 상태 Status | B36: =IF($B$33=0,"아직 계약 없음",IF($B$34>=$B$32,"손익분기 달성 — 계약 유효",IF('설정 Settings'!$C$15<='설정 Settings'!$C$106,"진행 중 — "&$B$35&"건 더 필요 (11/20까지)","무효 VOID — 모든 계약 무효, 보험·제설기 사지 않기"))) | C36: memo §2, §8
A37: 삽 제설 한도 Shovel cap | B37: =IF(AND($B$31="SHOVEL",$B$33>'설정 Settings'!$C$89),"한도 초과 — 삽 제설은 "&'설정 Settings'!$C$89&"곳까지 (가정)","OK") | C37: memo §9 (가정)
A38: 서명한 시즌 총액 Signed season value | B38: =SUMIFS('견적 Quotes'!$H$3:$H$1002,'견적 Quotes'!$G$3:$G$1002,"SNOW",'견적 Quotes'!$I$3:$I$1002,"WON") | C38: 받은 돈 ≠ 번 돈: 서비스를 한 만큼만 번 것 (memo 5.3)
A39: 월 분할 입금 예정 Per instalment (12/1–3/1) | B39: =IFERROR($B$38/'설정 Settings'!$C$87,0) | C39: 12/1, 1/1, 2/1, 3/1

Sheet 인보이스 Invoice
A1: ='설정 Settings'!$C$5 | E1: =IF(AND($H$7>0,$F$19>0,$F$20<=0),"영수증 RECEIPT","인보이스 INVOICE")
A2: ='설정 Settings'!$C$6
A3: ="주소 Address: "&'설정 Settings'!$C$7
A4: ="전화 Phone: "&'설정 Settings'!$C$8&" · 이메일 Email: "&'설정 Settings'!$C$9&" · 웹 Web: "&'설정 Settings'!$C$10
A6: 작업 ID Job ID (입력) | C6: =IF($B$6="","← 작업 ID를 입력하세요",IF($H$7=0,"작업 ID를 찾을 수 없음","")) | E6: 인보이스 번호 Invoice # | F6: =IF($B$6="","","INV-"&$B$6) | H6: helper
A7: 발행일 Invoice date | B7: =TODAY() | E7: 작업일 Service date | F7: =IF($H$7=0,"",INDEX('작업 Jobs'!$C$3:$C$1002,$H$7)) | H7: =IFERROR(MATCH($B$6,'작업 Jobs'!$A$3:$A$1002,0),0)
A8: 고객 Bill to | B8: =IF($H$7=0,"",INDEX('작업 Jobs'!$D$3:$D$1002,$H$7)) | H8: =IF($H$7=0,"",INDEX('작업 Jobs'!$F$3:$F$1002,$H$7))
A9: 작업 주소 Service address | B9: =IF($H$7=0,"",INDEX('작업 Jobs'!$E$3:$E$1002,$H$7)) | H9: =IF($H$7=0,"",INDEX('작업 Jobs'!$J$3:$J$1002,$H$7))
H10: =IF($H$7=0,"",INDEX('작업 Jobs'!$B$3:$B$1002,$H$7))
A11: 내용 Description | D11: 수량 Qty | E11: 단가 Unit $ | F11: 금액 Amount $ | H11: =IF($H$8<>"SNOW","",IFERROR(INDEX('견적 Quotes'!$H$3:$H$1002,MATCH($H$10,'견적 Quotes'!$A$3:$A$1002,0)),INDEX('작업 Jobs'!$H$3:$H$1002,$H$7)*'설정 Settings'!$C$87))
A12: =IF($H$7=0,"",IFERROR(VLOOKUP($H$8,'설정 Settings'!$A$122:$F$130,2,0)&" / "&VLOOKUP($H$8,'설정 Settings'!$A$122:$F$130,3,0),$H$8)) | D12: =IF($H$7=0,"",1) | E12: =IF($H$7=0,"",INDEX('작업 Jobs'!$H$3:$H$1002,$H$7)) | F12: =IF(OR($D$12="",$E$12=""),"",$D$12*$E$12) | H12: =IF(ISNUMBER($B$7),IF(MONTH($B$7)>=7,YEAR($B$7),YEAR($B$7)-1),YEAR('설정 Settings'!$C$15))
F13: =IF(OR($D$13="",$E$13=""),"",$D$13*$E$13) | H13: =$H$8="SNOW"
F14: =IF(OR($D$14="",$E$14=""),"",$D$14*$E$14)
F15: =IF(OR($D$15="",$E$15=""),"",$D$15*$E$15)
E16: 소계 Subtotal | F16: =SUM($F$12:$F$15)
A17: =IF('설정 Settings'!$C$24="YES","GST/HST 등록번호 Registration #: "&'설정 Settings'!$C$25,"") | E17: =IF('설정 Settings'!$C$24="YES",'설정 Settings'!$C$27,"") | F17: =IF('설정 Settings'!$C$24="YES",ROUND($F$16*'설정 Settings'!$C$26,2),"")
E18: 합계 Total | F18: =$F$16+IF('설정 Settings'!$C$24="YES",$F$17,0)
E19: 입금 Paid | F19: =IF($B$6="",0,SUMIFS('입금 Payments'!$C$3:$C$1002,'입금 Payments'!$B$3:$B$1002,$B$6))
E20: 잔액 Balance due | F20: =$F$18-$F$19
A22: 결제 방법 How to pay
A23: ="Interac e-Transfer: "&'설정 Settings'!$C$11&" — 메시지에 "&$F$6&" 번호를 적어 주세요. / Please put "&$F$6&" in the message."
A24: ="현금도 받습니다. / Cash is also accepted."&IF('설정 Settings'!$C$12="YES"," 카드 결제 가능. / Card accepted.","")
A25: =IF($F$18>'설정 Settings'!$C$36,"금액이 $2,000를 넘으면 은행 한도 때문에 e-Transfer를 두 번 이상 나눠 보내셔야 할 수 있습니다. / Amounts over $2,000 may need to be sent as two or more e-Transfers because of bank limits.","")
A26: =IF('설정 Settings'!$C$24="YES","","GST/HST 미등록 소규모 사업자로, 판매세를 부과하지 않았습니다. / Not registered for GST/HST (small supplier): no sales tax charged.")
A28: =IF($H$13,"제설 시즌 계약 — 4회 분할 / Snow season contract — 4 instalments","")
A29: =IF($H$13,"시즌 총액 / Season total","") | F29: =IF($H$13,$H$11,"")
A30: =IF($H$13,"1회차 / 1st","") | B30: =IF($H$13,DATE($H$12,12,1),"") | F30: =IF($H$13,ROUND(IFERROR($H$11/'설정 Settings'!$C$87,0),2),"")
A31: =IF($H$13,"2회차 / 2nd","") | B31: =IF($H$13,DATE($H$12+1,1,1),"") | F31: =IF($H$13,ROUND(IFERROR($H$11/'설정 Settings'!$C$87,0),2),"")
A32: =IF($H$13,"3회차 / 3rd","") | B32: =IF($H$13,DATE($H$12+1,2,1),"") | F32: =IF($H$13,ROUND(IFERROR($H$11/'설정 Settings'!$C$87,0),2),"")
A33: =IF($H$13,"4회차 / 4th","") | B33: =IF($H$13,DATE($H$12+1,3,1),"") | F33: =IF($H$13,ROUND(IFERROR($H$11/'설정 Settings'!$C$87,0),2),"")
A34: =IF($H$13,"12월 1일 전에는 어떤 금액도 받지 않습니다. / No payment is taken before Dec 1.","")
A35: =IF($H$13,"11월 20일까지 최소 계약 수가 채워지지 않으면 이 계약은 무효이며, 아무것도 청구하지 않습니다. / If the minimum number of contracts is not signed by Nov 20, this contract is void and nothing is charged.","")
A36: =IF($H$13,"시즌: 12월 1일–3월 31일. 11월 눈은 방문당 $"&'설정 Settings'!$C$86&". / Season: Dec 1 – Mar 31. November storms: $"&'설정 Settings'!$C$86&" per visit.","")
A38: =IF($H$9="Y",("온타리오 방문 계약: 집에서 서명하셨다면, 서명한 계약서 사본을 받은 날부터 10일 안에 취소할 수 있고, 환불은 15일 안에 받습니다. / Ontario: if you signed this agreement at your home, you can cancel within 10 days of receiving your signed copy, and any "&"refund is made within 15 days. (ontario.ca — 법률 자문 아님 / not legal advice)"),"")
A40: ="감사합니다! / Thank you!"
A41: ='설정 Settings'!$C$5&" · "&'설정 Settings'!$C$6&" · "&'설정 Settings'!$C$7&" · "&'설정 Settings'!$C$8&" · "&'설정 Settings'!$C$9

Sheet 지출 Expenses
A1: 날짜 Date | B1: 내용 Description | C1: 거래처 Vendor | D1: 금액 (세금 포함) Amount $ (incl. tax) | E1: T2125 분류 T2125 category | F1: 결제 방법 Paid by | G1: 영수증 보관? Receipt kept (Y/N) | H1: 관련 작업 ID Job ID (optional) | I1: 메모 Notes | J1: 주 시작 (일) Week start (Sun) | K1: 분기 Quarter
A2: 46294 | B2: EXAMPLE door-hanger printing | C2: EXAMPLE Print Shop | D2: 60 | E2: 8521 Advertising | F2: DEBIT | G2: Y | I2: 예시 행 — 계산에서 제외됨 / EXAMPLE row, not counted | J2: (자동) | K2: (자동)
J3: =IF($A3="","",$A3-WEEKDAY($A3,1)+1) | K3: =IF($A3="","",YEAR($A3)&"Q"&ROUNDUP(IFERROR(MONTH($A3)/3,0),0))
J4: =IF($A4="","",$A4-WEEKDAY($A4,1)+1) | K4: =IF($A4="","",YEAR($A4)&"Q"&ROUNDUP(IFERROR(MONTH($A4)/3,0),0))
J5: =IF($A5="","",$A5-WEEKDAY($A5,1)+1) | K5: =IF($A5="","",YEAR($A5)&"Q"&ROUNDUP(IFERROR(MONTH($A5)/3,0),0))
J6: =IF($A6="","",$A6-WEEKDAY($A6,1)+1) | K6: =IF($A6="","",YEAR($A6)&"Q"&ROUNDUP(IFERROR(MONTH($A6)/3,0),0))
J7: =IF($A7="","",$A7-WEEKDAY($A7,1)+1) | K7: =IF($A7="","",YEAR($A7)&"Q"&ROUNDUP(IFERROR(MONTH($A7)/3,0),0))
J8: =IF($A8="","",$A8-WEEKDAY($A8,1)+1) | K8: =IF($A8="","",YEAR($A8)&"Q"&ROUNDUP(IFERROR(MONTH($A8)/3,0),0))
J9: =IF($A9="","",$A9-WEEKDAY($A9,1)+1) | K9: =IF($A9="","",YEAR($A9)&"Q"&ROUNDUP(IFERROR(MONTH($A9)/3,0),0))
J10: =IF($A10="","",$A10-WEEKDAY($A10,1)+1) | K10: =IF($A10="","",YEAR($A10)&"Q"&ROUNDUP(IFERROR(MONTH($A10)/3,0),0))
J11: =IF($A11="","",$A11-WEEKDAY($A11,1)+1) | K11: =IF($A11="","",YEAR($A11)&"Q"&ROUNDUP(IFERROR(MONTH($A11)/3,0),0))
J12: =IF($A12="","",$A12-WEEKDAY($A12,1)+1) | K12: =IF($A12="","",YEAR($A12)&"Q"&ROUNDUP(IFERROR(MONTH($A12)/3,0),0))
J13: =IF($A13="","",$A13-WEEKDAY($A13,1)+1) | K13: =IF($A13="","",YEAR($A13)&"Q"&ROUNDUP(IFERROR(MONTH($A13)/3,0),0))
J14: =IF($A14="","",$A14-WEEKDAY($A14,1)+1) | K14: =IF($A14="","",YEAR($A14)&"Q"&ROUNDUP(IFERROR(MONTH($A14)/3,0),0))
... J1002: =IF($A1002="","",$A1002-WEEKDAY($A1002,1)+1) | K1002: =IF($A1002="","",YEAR($A1002)&"Q"&ROUNDUP(IFERROR(MONTH($A1002)/3,0),0))

Sheet 주행 Mileage
A1: 날짜 Date | B1: 출발 From | C1: 도착 To | D1: 업무 목적 Business purpose | E1: 관련 작업 ID Job ID | F1: 거리 (km) Distance (km) | G1: 메모 Notes | H1: 연도 Year
A2: 46309 | B2: Home | C2: 103 EXAMPLE St | D2: EXAMPLE job EX-J1 | E2: EX-J1 | F2: 12 | G2: 예시 행 — 계산에서 제외됨 / EXAMPLE row, not counted | H2: (자동)
H3: =IF($A3="","",YEAR($A3))
H4: =IF($A4="","",YEAR($A4))
H5: =IF($A5="","",YEAR($A5))
H6: =IF($A6="","",YEAR($A6))
H7: =IF($A7="","",YEAR($A7))
H8: =IF($A8="","",YEAR($A8))
H9: =IF($A9="","",YEAR($A9))
H10: =IF($A10="","",YEAR($A10))
H11: =IF($A11="","",YEAR($A11))
H12: =IF($A12="","",YEAR($A12))
H13: =IF($A13="","",YEAR($A13))
H14: =IF($A14="","",YEAR($A14))
... H1002: =IF($A1002="","",YEAR($A1002))
